{
  "provider": "gcp",
  "region": "europe-west1",
  "job_id": "projects/360779988854/locations/europe-west1/operations/9943662270638617183",
  "input_uri": "gs://skyflow-prototype-gcp-europe-west1/profile/videos/d7gY7YJ3Fdc.mp4",
  "annotation_result_count": 1,
  "shot_count": 1,
  "operation": {
    "name": "projects/360779988854/locations/europe-west1/operations/9943662270638617183",
    "metadata": {
      "@type": "type.googleapis.com/google.cloud.videointelligence.v1.AnnotateVideoProgress",
      "annotationProgress": [
        {
          "inputUri": "/skyflow-prototype-gcp-europe-west1/profile/videos/d7gY7YJ3Fdc.mp4",
          "progressPercent": 100,
          "startTime": "2026-06-23T08:52:25.513887Z",
          "updateTime": "2026-06-23T08:52:35.097355Z"
        }
      ]
    },
    "done": true,
    "response": {
      "@type": "type.googleapis.com/google.cloud.videointelligence.v1.AnnotateVideoResponse",
      "annotationResults": [
        {
          "inputUri": "/skyflow-prototype-gcp-europe-west1/profile/videos/d7gY7YJ3Fdc.mp4",
          "shotAnnotations": [
            {
              "startTimeOffset": "0s",
              "endTimeOffset": "11.763380s"
            }
          ],
          "segment": {
            "startTimeOffset": "0s",
            "endTimeOffset": "11.763380s"
          }
        }
      ]
    }
  }
}