{
  "provider": "gcp",
  "region": "asia-east1",
  "job_id": "projects/360779988854/locations/asia-east1/operations/4603667404746944776",
  "input_uri": "gs://skyflow-prototype-gcp-asia-east1/profile/videos/tjEMbP2SODQ.mp4",
  "annotation_result_count": 1,
  "shot_count": 4,
  "operation": {
    "name": "projects/360779988854/locations/asia-east1/operations/4603667404746944776",
    "metadata": {
      "@type": "type.googleapis.com/google.cloud.videointelligence.v1.AnnotateVideoProgress",
      "annotationProgress": [
        {
          "inputUri": "/skyflow-prototype-gcp-asia-east1/profile/videos/tjEMbP2SODQ.mp4",
          "progressPercent": 100,
          "startTime": "2026-06-23T07:31:16.597615Z",
          "updateTime": "2026-06-23T07:31:30.202430Z"
        }
      ]
    },
    "done": true,
    "response": {
      "@type": "type.googleapis.com/google.cloud.videointelligence.v1.AnnotateVideoResponse",
      "annotationResults": [
        {
          "inputUri": "/skyflow-prototype-gcp-asia-east1/profile/videos/tjEMbP2SODQ.mp4",
          "shotAnnotations": [
            {
              "startTimeOffset": "0s",
              "endTimeOffset": "74.566666s"
            },
            {
              "startTimeOffset": "74.600s",
              "endTimeOffset": "131.133333s"
            },
            {
              "startTimeOffset": "131.166666s",
              "endTimeOffset": "146.466666s"
            },
            {
              "startTimeOffset": "146.500s",
              "endTimeOffset": "180.333333s"
            }
          ],
          "segment": {
            "startTimeOffset": "0s",
            "endTimeOffset": "180.333333s"
          }
        }
      ]
    }
  }
}