[
  {
    "workflow": "workflow1",
    "quality_level": "Q1",
    "query_count": 200,
    "eta": 0.1,
    "calibration_scenarios_per_query": 50,
    "test_scenarios_per_query": NaN,
    "calibration_scenario_count": 10000,
    "test_scenario_count": NaN,
    "method": "full_milp",
    "solver_method": NaN,
    "status": "FAILED",
    "reused_last_feasible": false,
    "objective_value": NaN,
    "expected_cost": NaN,
    "avg_latency": NaN,
    "p95_latency": NaN,
    "p99_latency": NaN,
    "violation_rate": NaN,
    "solver_runtime_sec": NaN,
    "wall_time_sec": 22.42808929199964,
    "max_rss_mb": 1351.734375,
    "num_iterations": 0,
    "active_scenario_count": 0,
    "active_scenario_fraction": NaN,
    "assignment_signature": NaN,
    "error": "RuntimeError: Full MILP failed to find a solution (status=INFEASIBLE)\nTraceback (most recent call last):\n  File \"/Users/heng/Documents/skybridge/sim/scripts/run_q_scaling_full_decomp_minp95.py\", line 89, in _worker\n    result = solve_full_milp(\n        workflow,\n    ...<4 lines>...\n        config,\n    )\n  File \"/Users/heng/Documents/skybridge/sim/src/milp_full.py\", line 50, in solve_full_milp\n    raise RuntimeError(f\"Full MILP failed to find a solution (status={status})\")\nRuntimeError: Full MILP failed to find a solution (status=INFEASIBLE)\n",
    "process_exitcode": 0
  },
  {
    "workflow": "workflow1",
    "quality_level": "Q1",
    "query_count": 200,
    "eta": 0.1,
    "calibration_scenarios_per_query": 50,
    "test_scenarios_per_query": 50.0,
    "calibration_scenario_count": 10000,
    "test_scenario_count": 10000.0,
    "method": "decomposed_milp",
    "solver_method": "decomposition",
    "status": "INFEASIBLE_REUSED_LAST_FEASIBLE",
    "reused_last_feasible": true,
    "objective_value": Infinity,
    "expected_cost": 1.151633439511564,
    "avg_latency": 503.7282317299979,
    "p95_latency": 1222.104056773627,
    "p99_latency": 1968.6067221430371,
    "violation_rate": 0.0374,
    "solver_runtime_sec": 8.911463082999035,
    "wall_time_sec": 31.6467915000012,
    "max_rss_mb": 1137.234375,
    "num_iterations": 3,
    "active_scenario_count": 3000,
    "active_scenario_fraction": 0.3,
    "assignment_signature": "[[\"Q/A\", \"q_a_aws_us-east-2_q1\"], [\"Shot Detection\", \"shot_detection_aliyun_cn-shanghai_q1\"], [\"Video Caption\", \"video_caption_aws_us-east-2_q1\"], [\"Video Split & Sample\", \"video_split_and_sample_aliyun_cn-shanghai_q1\"]]",
    "error": NaN,
    "process_exitcode": 0
  },
  {
    "workflow": "workflow1",
    "quality_level": "Q1",
    "query_count": 400,
    "eta": 0.1,
    "calibration_scenarios_per_query": 50,
    "test_scenarios_per_query": NaN,
    "calibration_scenario_count": 20000,
    "test_scenario_count": NaN,
    "method": "full_milp",
    "solver_method": NaN,
    "status": "FAILED",
    "reused_last_feasible": false,
    "objective_value": NaN,
    "expected_cost": NaN,
    "avg_latency": NaN,
    "p95_latency": NaN,
    "p99_latency": NaN,
    "violation_rate": NaN,
    "solver_runtime_sec": NaN,
    "wall_time_sec": 79.20901687500009,
    "max_rss_mb": 2169.09375,
    "num_iterations": 0,
    "active_scenario_count": 0,
    "active_scenario_fraction": NaN,
    "assignment_signature": NaN,
    "error": "RuntimeError: Full MILP failed to find a solution (status=INFEASIBLE)\nTraceback (most recent call last):\n  File \"/Users/heng/Documents/skybridge/sim/scripts/run_q_scaling_full_decomp_minp95.py\", line 89, in _worker\n    result = solve_full_milp(\n        workflow,\n    ...<4 lines>...\n        config,\n    )\n  File \"/Users/heng/Documents/skybridge/sim/src/milp_full.py\", line 50, in solve_full_milp\n    raise RuntimeError(f\"Full MILP failed to find a solution (status={status})\")\nRuntimeError: Full MILP failed to find a solution (status=INFEASIBLE)\n",
    "process_exitcode": 0
  },
  {
    "workflow": "workflow1",
    "quality_level": "Q1",
    "query_count": 400,
    "eta": 0.1,
    "calibration_scenarios_per_query": 50,
    "test_scenarios_per_query": 50.0,
    "calibration_scenario_count": 20000,
    "test_scenario_count": 20000.0,
    "method": "decomposed_milp",
    "solver_method": "decomposition",
    "status": "INFEASIBLE_REUSED_LAST_FEASIBLE",
    "reused_last_feasible": true,
    "objective_value": Infinity,
    "expected_cost": 1.19612104403649,
    "avg_latency": 521.9028679278351,
    "p95_latency": 1249.921194637467,
    "p99_latency": 1963.0210849314371,
    "violation_rate": 0.03555,
    "solver_runtime_sec": 30.09457199999997,
    "wall_time_sec": 63.30264070900011,
    "max_rss_mb": 1300.65625,
    "num_iterations": 3,
    "active_scenario_count": 6000,
    "active_scenario_fraction": 0.3,
    "assignment_signature": "[[\"Q/A\", \"q_a_aws_us-east-2_q1\"], [\"Shot Detection\", \"shot_detection_aliyun_cn-shanghai_q1\"], [\"Video Caption\", \"video_caption_aws_us-east-2_q1\"], [\"Video Split & Sample\", \"video_split_and_sample_aliyun_cn-shanghai_q1\"]]",
    "error": NaN,
    "process_exitcode": 0
  },
  {
    "workflow": "workflow1",
    "quality_level": "Q1",
    "query_count": 600,
    "eta": 0.1,
    "calibration_scenarios_per_query": 50,
    "test_scenarios_per_query": NaN,
    "calibration_scenario_count": 30000,
    "test_scenario_count": NaN,
    "method": "full_milp",
    "solver_method": NaN,
    "status": "FAILED",
    "reused_last_feasible": false,
    "objective_value": NaN,
    "expected_cost": NaN,
    "avg_latency": NaN,
    "p95_latency": NaN,
    "p99_latency": NaN,
    "violation_rate": NaN,
    "solver_runtime_sec": NaN,
    "wall_time_sec": 242.0804341250005,
    "max_rss_mb": 3004.796875,
    "num_iterations": 0,
    "active_scenario_count": 0,
    "active_scenario_fraction": NaN,
    "assignment_signature": NaN,
    "error": "RuntimeError: Full MILP failed to find a solution (status=INFEASIBLE)\nTraceback (most recent call last):\n  File \"/Users/heng/Documents/skybridge/sim/scripts/run_q_scaling_full_decomp_minp95.py\", line 89, in _worker\n    result = solve_full_milp(\n        workflow,\n    ...<4 lines>...\n        config,\n    )\n  File \"/Users/heng/Documents/skybridge/sim/src/milp_full.py\", line 50, in solve_full_milp\n    raise RuntimeError(f\"Full MILP failed to find a solution (status={status})\")\nRuntimeError: Full MILP failed to find a solution (status=INFEASIBLE)\n",
    "process_exitcode": 0
  },
  {
    "workflow": "workflow1",
    "quality_level": "Q1",
    "query_count": 600,
    "eta": 0.1,
    "calibration_scenarios_per_query": 50,
    "test_scenarios_per_query": 50.0,
    "calibration_scenario_count": 30000,
    "test_scenario_count": 30000.0,
    "method": "decomposed_milp",
    "solver_method": "decomposition",
    "status": "INFEASIBLE_REUSED_LAST_FEASIBLE",
    "reused_last_feasible": true,
    "objective_value": Infinity,
    "expected_cost": 1.1996516248526408,
    "avg_latency": 523.9177747037106,
    "p95_latency": 1259.997149193707,
    "p99_latency": 1985.667386718514,
    "violation_rate": 0.0357,
    "solver_runtime_sec": 54.52772349999759,
    "wall_time_sec": 98.14246279100009,
    "max_rss_mb": 1542.0625,
    "num_iterations": 3,
    "active_scenario_count": 9000,
    "active_scenario_fraction": 0.3,
    "assignment_signature": "[[\"Q/A\", \"q_a_aws_us-east-2_q1\"], [\"Shot Detection\", \"shot_detection_aliyun_cn-shanghai_q1\"], [\"Video Caption\", \"video_caption_aws_us-east-2_q1\"], [\"Video Split & Sample\", \"video_split_and_sample_aliyun_cn-shanghai_q1\"]]",
    "error": NaN,
    "process_exitcode": 0
  },
  {
    "workflow": "workflow1",
    "quality_level": "Q1",
    "query_count": 800,
    "eta": 0.1,
    "calibration_scenarios_per_query": 50,
    "test_scenarios_per_query": NaN,
    "calibration_scenario_count": 40000,
    "test_scenario_count": NaN,
    "method": "full_milp",
    "solver_method": NaN,
    "status": "FAILED",
    "reused_last_feasible": false,
    "objective_value": NaN,
    "expected_cost": NaN,
    "avg_latency": NaN,
    "p95_latency": NaN,
    "p99_latency": NaN,
    "violation_rate": NaN,
    "solver_runtime_sec": NaN,
    "wall_time_sec": 408.6945377079992,
    "max_rss_mb": 3545.8125,
    "num_iterations": 0,
    "active_scenario_count": 0,
    "active_scenario_fraction": NaN,
    "assignment_signature": NaN,
    "error": "RuntimeError: Full MILP failed to find a solution (status=INFEASIBLE)\nTraceback (most recent call last):\n  File \"/Users/heng/Documents/skybridge/sim/scripts/run_q_scaling_full_decomp_minp95.py\", line 89, in _worker\n    result = solve_full_milp(\n        workflow,\n    ...<4 lines>...\n        config,\n    )\n  File \"/Users/heng/Documents/skybridge/sim/src/milp_full.py\", line 50, in solve_full_milp\n    raise RuntimeError(f\"Full MILP failed to find a solution (status={status})\")\nRuntimeError: Full MILP failed to find a solution (status=INFEASIBLE)\n",
    "process_exitcode": 0
  },
  {
    "workflow": "workflow1",
    "quality_level": "Q1",
    "query_count": 800,
    "eta": 0.1,
    "calibration_scenarios_per_query": 50,
    "test_scenarios_per_query": 50.0,
    "calibration_scenario_count": 40000,
    "test_scenario_count": 40000.0,
    "method": "decomposed_milp",
    "solver_method": "decomposition",
    "status": "INFEASIBLE_REUSED_LAST_FEASIBLE",
    "reused_last_feasible": true,
    "objective_value": Infinity,
    "expected_cost": 1.2079414840372198,
    "avg_latency": 525.9976949958237,
    "p95_latency": 1263.440618464427,
    "p99_latency": 1983.172434601083,
    "violation_rate": 0.036375,
    "solver_runtime_sec": 129.4962626659999,
    "wall_time_sec": 182.49750533399856,
    "max_rss_mb": 1803.96875,
    "num_iterations": 3,
    "active_scenario_count": 12000,
    "active_scenario_fraction": 0.3,
    "assignment_signature": "[[\"Q/A\", \"q_a_aws_us-east-2_q1\"], [\"Shot Detection\", \"shot_detection_aliyun_cn-shanghai_q1\"], [\"Video Caption\", \"video_caption_aws_us-east-2_q1\"], [\"Video Split & Sample\", \"video_split_and_sample_aliyun_cn-shanghai_q1\"]]",
    "error": NaN,
    "process_exitcode": 0
  },
  {
    "workflow": "workflow1",
    "quality_level": "Q1",
    "query_count": 1000,
    "eta": 0.1,
    "calibration_scenarios_per_query": 50,
    "test_scenarios_per_query": NaN,
    "calibration_scenario_count": 50000,
    "test_scenario_count": NaN,
    "method": "full_milp",
    "solver_method": NaN,
    "status": "FAILED",
    "reused_last_feasible": false,
    "objective_value": NaN,
    "expected_cost": NaN,
    "avg_latency": NaN,
    "p95_latency": NaN,
    "p99_latency": NaN,
    "violation_rate": NaN,
    "solver_runtime_sec": NaN,
    "wall_time_sec": 377.91674008300106,
    "max_rss_mb": 4522.546875,
    "num_iterations": 0,
    "active_scenario_count": 0,
    "active_scenario_fraction": NaN,
    "assignment_signature": NaN,
    "error": "RuntimeError: Full MILP failed to find a solution (status=TIME_LIMIT)\nTraceback (most recent call last):\n  File \"/Users/heng/Documents/skybridge/sim/scripts/run_q_scaling_full_decomp_minp95.py\", line 89, in _worker\n    result = solve_full_milp(\n        workflow,\n    ...<4 lines>...\n        config,\n    )\n  File \"/Users/heng/Documents/skybridge/sim/src/milp_full.py\", line 50, in solve_full_milp\n    raise RuntimeError(f\"Full MILP failed to find a solution (status={status})\")\nRuntimeError: Full MILP failed to find a solution (status=TIME_LIMIT)\n",
    "process_exitcode": 0
  },
  {
    "workflow": "workflow1",
    "quality_level": "Q1",
    "query_count": 1000,
    "eta": 0.1,
    "calibration_scenarios_per_query": 50,
    "test_scenarios_per_query": 50.0,
    "calibration_scenario_count": 50000,
    "test_scenario_count": 50000.0,
    "method": "decomposed_milp",
    "solver_method": "decomposition",
    "status": "INFEASIBLE_REUSED_LAST_FEASIBLE",
    "reused_last_feasible": true,
    "objective_value": Infinity,
    "expected_cost": 1.2130651597532884,
    "avg_latency": 528.0033739582669,
    "p95_latency": 1260.508716279426,
    "p99_latency": 1970.8942198091147,
    "violation_rate": 0.03566,
    "solver_runtime_sec": 182.86600333300157,
    "wall_time_sec": 247.06540754200068,
    "max_rss_mb": 2204.984375,
    "num_iterations": 3,
    "active_scenario_count": 15000,
    "active_scenario_fraction": 0.3,
    "assignment_signature": "[[\"Q/A\", \"q_a_aws_us-east-2_q1\"], [\"Shot Detection\", \"shot_detection_aliyun_cn-shanghai_q1\"], [\"Video Caption\", \"video_caption_aws_us-east-2_q1\"], [\"Video Split & Sample\", \"video_split_and_sample_aliyun_cn-shanghai_q1\"]]",
    "error": NaN,
    "process_exitcode": 0
  },
  {
    "workflow": "workflow1",
    "quality_level": "Q1",
    "query_count": 1200,
    "eta": 0.1,
    "calibration_scenarios_per_query": 50,
    "test_scenarios_per_query": NaN,
    "calibration_scenario_count": 60000,
    "test_scenario_count": NaN,
    "method": "full_milp",
    "solver_method": NaN,
    "status": "FAILED",
    "reused_last_feasible": false,
    "objective_value": NaN,
    "expected_cost": NaN,
    "avg_latency": NaN,
    "p95_latency": NaN,
    "p99_latency": NaN,
    "violation_rate": NaN,
    "solver_runtime_sec": NaN,
    "wall_time_sec": 522.3940470000016,
    "max_rss_mb": 5229.0625,
    "num_iterations": 0,
    "active_scenario_count": 0,
    "active_scenario_fraction": NaN,
    "assignment_signature": NaN,
    "error": "RuntimeError: Full MILP failed to find a solution (status=TIME_LIMIT)\nTraceback (most recent call last):\n  File \"/Users/heng/Documents/skybridge/sim/scripts/run_q_scaling_full_decomp_minp95.py\", line 89, in _worker\n    result = solve_full_milp(\n        workflow,\n    ...<4 lines>...\n        config,\n    )\n  File \"/Users/heng/Documents/skybridge/sim/src/milp_full.py\", line 50, in solve_full_milp\n    raise RuntimeError(f\"Full MILP failed to find a solution (status={status})\")\nRuntimeError: Full MILP failed to find a solution (status=TIME_LIMIT)\n",
    "process_exitcode": 0
  },
  {
    "workflow": "workflow1",
    "quality_level": "Q1",
    "query_count": 1200,
    "eta": 0.1,
    "calibration_scenarios_per_query": 50,
    "test_scenarios_per_query": 50,
    "calibration_scenario_count": 60000,
    "test_scenario_count": 60000,
    "method": "decomposed_milp",
    "solver_method": "decomposition",
    "status": "INFEASIBLE_REUSED_LAST_FEASIBLE",
    "reused_last_feasible": true,
    "objective_value": Infinity,
    "expected_cost": 1.2174333160666815,
    "avg_latency": 529.928389835214,
    "p95_latency": 1265.1772056328273,
    "p99_latency": 1976.8299551600776,
    "violation_rate": 0.03593333333333333,
    "solver_runtime_sec": 223.28737920799904,
    "wall_time_sec": 297.8673292500007,
    "max_rss_mb": 2395.71875,
    "num_iterations": 3,
    "active_scenario_count": 18000,
    "active_scenario_fraction": 0.3,
    "assignment_signature": "[[\"Q/A\", \"q_a_aws_us-east-2_q1\"], [\"Shot Detection\", \"shot_detection_aliyun_cn-shanghai_q1\"], [\"Video Caption\", \"video_caption_aws_us-east-2_q1\"], [\"Video Split & Sample\", \"video_split_and_sample_aliyun_cn-shanghai_q1\"]]",
    "error": "",
    "process_exitcode": 0
  },
  {
    "workflow": "workflow1",
    "quality_level": "Q1",
    "query_count": 1400,
    "eta": 0.1,
    "calibration_scenarios_per_query": 50,
    "test_scenarios_per_query": NaN,
    "calibration_scenario_count": 70000,
    "test_scenario_count": NaN,
    "method": "full_milp",
    "solver_method": "",
    "status": "FAILED",
    "reused_last_feasible": false,
    "objective_value": NaN,
    "expected_cost": NaN,
    "avg_latency": NaN,
    "p95_latency": NaN,
    "p99_latency": NaN,
    "violation_rate": NaN,
    "solver_runtime_sec": NaN,
    "wall_time_sec": 597.6934907910018,
    "max_rss_mb": 5423.9375,
    "num_iterations": 0,
    "active_scenario_count": 0,
    "active_scenario_fraction": NaN,
    "assignment_signature": "",
    "error": "RuntimeError: Full MILP failed to find a solution (status=TIME_LIMIT)\nTraceback (most recent call last):\n  File \"/Users/heng/Documents/skybridge/sim/scripts/run_q_scaling_full_decomp_minp95.py\", line 89, in _worker\n    result = solve_full_milp(\n        workflow,\n    ...<4 lines>...\n        config,\n    )\n  File \"/Users/heng/Documents/skybridge/sim/src/milp_full.py\", line 50, in solve_full_milp\n    raise RuntimeError(f\"Full MILP failed to find a solution (status={status})\")\nRuntimeError: Full MILP failed to find a solution (status=TIME_LIMIT)\n",
    "process_exitcode": 0
  },
  {
    "workflow": "workflow1",
    "quality_level": "Q1",
    "query_count": 1400,
    "eta": 0.1,
    "calibration_scenarios_per_query": 50,
    "test_scenarios_per_query": 50,
    "calibration_scenario_count": 70000,
    "test_scenario_count": 70000,
    "method": "decomposed_milp",
    "solver_method": "decomposition",
    "status": "INFEASIBLE_REUSED_LAST_FEASIBLE",
    "reused_last_feasible": true,
    "objective_value": Infinity,
    "expected_cost": 1.2181114964308433,
    "avg_latency": 530.2486872489018,
    "p95_latency": 1263.3535975235245,
    "p99_latency": 1966.8164413952793,
    "violation_rate": 0.03567142857142857,
    "solver_runtime_sec": 320.8777849580001,
    "wall_time_sec": 404.4294437089993,
    "max_rss_mb": 2766.421875,
    "num_iterations": 3,
    "active_scenario_count": 21000,
    "active_scenario_fraction": 0.3,
    "assignment_signature": "[[\"Q/A\", \"q_a_aws_us-east-2_q1\"], [\"Shot Detection\", \"shot_detection_aliyun_cn-shanghai_q1\"], [\"Video Caption\", \"video_caption_aws_us-east-2_q1\"], [\"Video Split & Sample\", \"video_split_and_sample_aliyun_cn-shanghai_q1\"]]",
    "error": "",
    "process_exitcode": 0
  },
  {
    "workflow": "workflow1",
    "quality_level": "Q1",
    "query_count": 1600,
    "eta": 0.1,
    "calibration_scenarios_per_query": 50,
    "test_scenarios_per_query": NaN,
    "calibration_scenario_count": 80000,
    "test_scenario_count": NaN,
    "method": "full_milp",
    "solver_method": "",
    "status": "FAILED",
    "reused_last_feasible": false,
    "objective_value": NaN,
    "expected_cost": NaN,
    "avg_latency": NaN,
    "p95_latency": NaN,
    "p99_latency": NaN,
    "violation_rate": NaN,
    "solver_runtime_sec": NaN,
    "wall_time_sec": 277.082440457998,
    "max_rss_mb": 5600.734375,
    "num_iterations": 0,
    "active_scenario_count": 0,
    "active_scenario_fraction": NaN,
    "assignment_signature": "",
    "error": "RuntimeError: Full MILP failed to find a solution (status=INFEASIBLE)\nTraceback (most recent call last):\n  File \"/Users/heng/Documents/skybridge/sim/scripts/run_q_scaling_full_decomp_minp95.py\", line 89, in _worker\n    result = solve_full_milp(\n        workflow,\n    ...<4 lines>...\n        config,\n    )\n  File \"/Users/heng/Documents/skybridge/sim/src/milp_full.py\", line 50, in solve_full_milp\n    raise RuntimeError(f\"Full MILP failed to find a solution (status={status})\")\nRuntimeError: Full MILP failed to find a solution (status=INFEASIBLE)\n",
    "process_exitcode": 0
  },
  {
    "workflow": "workflow1",
    "quality_level": "Q1",
    "query_count": 1600,
    "eta": 0.1,
    "calibration_scenarios_per_query": 50,
    "test_scenarios_per_query": 50,
    "calibration_scenario_count": 80000,
    "test_scenario_count": 80000,
    "method": "decomposed_milp",
    "solver_method": "decomposition",
    "status": "INFEASIBLE_REUSED_LAST_FEASIBLE",
    "reused_last_feasible": true,
    "objective_value": Infinity,
    "expected_cost": 1.2248911892621839,
    "avg_latency": 533.0397454445755,
    "p95_latency": 1261.856505168361,
    "p99_latency": 1966.7194365073697,
    "violation_rate": 0.035825,
    "solver_runtime_sec": 194.88623641700178,
    "wall_time_sec": 288.80951829100013,
    "max_rss_mb": 3126.9375,
    "num_iterations": 3,
    "active_scenario_count": 24000,
    "active_scenario_fraction": 0.3,
    "assignment_signature": "[[\"Q/A\", \"q_a_aws_us-east-2_q1\"], [\"Shot Detection\", \"shot_detection_aliyun_cn-shanghai_q1\"], [\"Video Caption\", \"video_caption_aws_us-east-2_q1\"], [\"Video Split & Sample\", \"video_split_and_sample_aliyun_cn-shanghai_q1\"]]",
    "error": "",
    "process_exitcode": 0
  },
  {
    "workflow": "workflow1",
    "quality_level": "Q1",
    "query_count": 1800,
    "eta": 0.1,
    "calibration_scenarios_per_query": 50,
    "test_scenarios_per_query": NaN,
    "calibration_scenario_count": 90000,
    "test_scenario_count": NaN,
    "method": "full_milp",
    "solver_method": "",
    "status": "FAILED",
    "reused_last_feasible": false,
    "objective_value": NaN,
    "expected_cost": NaN,
    "avg_latency": NaN,
    "p95_latency": NaN,
    "p99_latency": NaN,
    "violation_rate": NaN,
    "solver_runtime_sec": NaN,
    "wall_time_sec": 563.4444178330014,
    "max_rss_mb": 5849.265625,
    "num_iterations": 0,
    "active_scenario_count": 0,
    "active_scenario_fraction": NaN,
    "assignment_signature": "",
    "error": "RuntimeError: Full MILP failed to find a solution (status=TIME_LIMIT)\nTraceback (most recent call last):\n  File \"/Users/heng/Documents/skybridge/sim/scripts/run_q_scaling_full_decomp_minp95.py\", line 89, in _worker\n    result = solve_full_milp(\n        workflow,\n    ...<4 lines>...\n        config,\n    )\n  File \"/Users/heng/Documents/skybridge/sim/src/milp_full.py\", line 50, in solve_full_milp\n    raise RuntimeError(f\"Full MILP failed to find a solution (status={status})\")\nRuntimeError: Full MILP failed to find a solution (status=TIME_LIMIT)\n",
    "process_exitcode": 0
  },
  {
    "workflow": "workflow1",
    "quality_level": "Q1",
    "query_count": 1800,
    "eta": 0.1,
    "calibration_scenarios_per_query": 50,
    "test_scenarios_per_query": 50,
    "calibration_scenario_count": 90000,
    "test_scenario_count": 90000,
    "method": "decomposed_milp",
    "solver_method": "decomposition",
    "status": "INFEASIBLE_REUSED_LAST_FEASIBLE",
    "reused_last_feasible": true,
    "objective_value": Infinity,
    "expected_cost": 1.2293115237813022,
    "avg_latency": 534.4708695110266,
    "p95_latency": 1262.6365083097344,
    "p99_latency": 1970.786664750983,
    "violation_rate": 0.036,
    "solver_runtime_sec": 476.72863566699743,
    "wall_time_sec": 581.0180573340003,
    "max_rss_mb": 3510.8125,
    "num_iterations": 3,
    "active_scenario_count": 27000,
    "active_scenario_fraction": 0.3,
    "assignment_signature": "[[\"Q/A\", \"q_a_aws_us-east-2_q1\"], [\"Shot Detection\", \"shot_detection_aliyun_cn-shanghai_q1\"], [\"Video Caption\", \"video_caption_aws_us-east-2_q1\"], [\"Video Split & Sample\", \"video_split_and_sample_aliyun_cn-shanghai_q1\"]]",
    "error": "",
    "process_exitcode": 0
  },
  {
    "workflow": "workflow1",
    "quality_level": "Q1",
    "query_count": 2000,
    "eta": 0.1,
    "calibration_scenarios_per_query": 50,
    "test_scenarios_per_query": NaN,
    "calibration_scenario_count": 100000,
    "test_scenario_count": NaN,
    "method": "full_milp",
    "solver_method": "",
    "status": "FAILED",
    "reused_last_feasible": false,
    "objective_value": NaN,
    "expected_cost": NaN,
    "avg_latency": NaN,
    "p95_latency": NaN,
    "p99_latency": NaN,
    "violation_rate": NaN,
    "solver_runtime_sec": NaN,
    "wall_time_sec": 815.7532612920004,
    "max_rss_mb": 5922.1875,
    "num_iterations": 0,
    "active_scenario_count": 0,
    "active_scenario_fraction": NaN,
    "assignment_signature": "",
    "error": "RuntimeError: Full MILP failed to find a solution (status=TIME_LIMIT)\nTraceback (most recent call last):\n  File \"/Users/heng/Documents/skybridge/sim/scripts/run_q_scaling_full_decomp_minp95.py\", line 89, in _worker\n    result = solve_full_milp(\n        workflow,\n    ...<4 lines>...\n        config,\n    )\n  File \"/Users/heng/Documents/skybridge/sim/src/milp_full.py\", line 50, in solve_full_milp\n    raise RuntimeError(f\"Full MILP failed to find a solution (status={status})\")\nRuntimeError: Full MILP failed to find a solution (status=TIME_LIMIT)\n",
    "process_exitcode": 0
  },
  {
    "workflow": "workflow1",
    "quality_level": "Q1",
    "query_count": 2000,
    "eta": 0.1,
    "calibration_scenarios_per_query": 50,
    "test_scenarios_per_query": 50,
    "calibration_scenario_count": 100000,
    "test_scenario_count": 100000,
    "method": "decomposed_milp",
    "solver_method": "decomposition",
    "status": "INFEASIBLE_REUSED_LAST_FEASIBLE",
    "reused_last_feasible": true,
    "objective_value": Infinity,
    "expected_cost": 1.2274167973991148,
    "avg_latency": 533.7324154462528,
    "p95_latency": 1260.2418665825226,
    "p99_latency": 1968.0684122295856,
    "violation_rate": 0.03567,
    "solver_runtime_sec": 560.4820958759992,
    "wall_time_sec": 674.5948676670014,
    "max_rss_mb": 3698.109375,
    "num_iterations": 3,
    "active_scenario_count": 30000,
    "active_scenario_fraction": 0.3,
    "assignment_signature": "[[\"Q/A\", \"q_a_aws_us-east-2_q1\"], [\"Shot Detection\", \"shot_detection_aliyun_cn-shanghai_q1\"], [\"Video Caption\", \"video_caption_aws_us-east-2_q1\"], [\"Video Split & Sample\", \"video_split_and_sample_aliyun_cn-shanghai_q1\"]]",
    "error": "",
    "process_exitcode": 0
  },
  {
    "workflow": "workflow1",
    "quality_level": "Q2",
    "query_count": 200,
    "eta": 0.1,
    "calibration_scenarios_per_query": 50,
    "test_scenarios_per_query": NaN,
    "calibration_scenario_count": 10000,
    "test_scenario_count": NaN,
    "method": "full_milp",
    "solver_method": "",
    "status": "FAILED",
    "reused_last_feasible": false,
    "objective_value": NaN,
    "expected_cost": NaN,
    "avg_latency": NaN,
    "p95_latency": NaN,
    "p99_latency": NaN,
    "violation_rate": NaN,
    "solver_runtime_sec": NaN,
    "wall_time_sec": 20.135003791998315,
    "max_rss_mb": 1203.1875,
    "num_iterations": 0,
    "active_scenario_count": 0,
    "active_scenario_fraction": NaN,
    "assignment_signature": "",
    "error": "RuntimeError: Full MILP failed to find a solution (status=INFEASIBLE)\nTraceback (most recent call last):\n  File \"/Users/heng/Documents/skybridge/sim/scripts/run_q_scaling_full_decomp_minp95.py\", line 89, in _worker\n    result = solve_full_milp(\n        workflow,\n    ...<4 lines>...\n        config,\n    )\n  File \"/Users/heng/Documents/skybridge/sim/src/milp_full.py\", line 50, in solve_full_milp\n    raise RuntimeError(f\"Full MILP failed to find a solution (status={status})\")\nRuntimeError: Full MILP failed to find a solution (status=INFEASIBLE)\n",
    "process_exitcode": 0
  },
  {
    "workflow": "workflow1",
    "quality_level": "Q2",
    "query_count": 200,
    "eta": 0.1,
    "calibration_scenarios_per_query": 50,
    "test_scenarios_per_query": 50,
    "calibration_scenario_count": 10000,
    "test_scenario_count": 10000,
    "method": "decomposed_milp",
    "solver_method": "decomposition",
    "status": "INFEASIBLE_REUSED_LAST_FEASIBLE",
    "reused_last_feasible": true,
    "objective_value": Infinity,
    "expected_cost": 2.9213922769637892,
    "avg_latency": 2017.0924429135353,
    "p95_latency": 5769.815636449157,
    "p99_latency": 9762.685512233214,
    "violation_rate": 0.0396,
    "solver_runtime_sec": 9.494595667001704,
    "wall_time_sec": 30.97140458300055,
    "max_rss_mb": 1175.234375,
    "num_iterations": 3,
    "active_scenario_count": 3000,
    "active_scenario_fraction": 0.3,
    "assignment_signature": "[[\"Q/A\", \"q_a_aws_us-east-2_q2\"], [\"Shot Detection\", \"shot_detection_aliyun_cn-shanghai_q2\"], [\"Video Caption\", \"video_caption_aws_us-east-2_q2\"], [\"Video Split & Sample\", \"video_split_and_sample_aliyun_cn-shanghai_q2\"]]",
    "error": "",
    "process_exitcode": 0
  },
  {
    "workflow": "workflow1",
    "quality_level": "Q2",
    "query_count": 400,
    "eta": 0.1,
    "calibration_scenarios_per_query": 50,
    "test_scenarios_per_query": NaN,
    "calibration_scenario_count": 20000,
    "test_scenario_count": NaN,
    "method": "full_milp",
    "solver_method": "",
    "status": "FAILED",
    "reused_last_feasible": false,
    "objective_value": NaN,
    "expected_cost": NaN,
    "avg_latency": NaN,
    "p95_latency": NaN,
    "p99_latency": NaN,
    "violation_rate": NaN,
    "solver_runtime_sec": NaN,
    "wall_time_sec": 85.37848266700166,
    "max_rss_mb": 2082.890625,
    "num_iterations": 0,
    "active_scenario_count": 0,
    "active_scenario_fraction": NaN,
    "assignment_signature": "",
    "error": "RuntimeError: Full MILP failed to find a solution (status=INFEASIBLE)\nTraceback (most recent call last):\n  File \"/Users/heng/Documents/skybridge/sim/scripts/run_q_scaling_full_decomp_minp95.py\", line 89, in _worker\n    result = solve_full_milp(\n        workflow,\n    ...<4 lines>...\n        config,\n    )\n  File \"/Users/heng/Documents/skybridge/sim/src/milp_full.py\", line 50, in solve_full_milp\n    raise RuntimeError(f\"Full MILP failed to find a solution (status={status})\")\nRuntimeError: Full MILP failed to find a solution (status=INFEASIBLE)\n",
    "process_exitcode": 0
  },
  {
    "workflow": "workflow1",
    "quality_level": "Q2",
    "query_count": 400,
    "eta": 0.1,
    "calibration_scenarios_per_query": 50,
    "test_scenarios_per_query": 50,
    "calibration_scenario_count": 20000,
    "test_scenario_count": 20000,
    "method": "decomposed_milp",
    "solver_method": "decomposition",
    "status": "INFEASIBLE_REUSED_LAST_FEASIBLE",
    "reused_last_feasible": true,
    "objective_value": Infinity,
    "expected_cost": 2.8212529483740982,
    "avg_latency": 1952.1411188272239,
    "p95_latency": 5651.273482245171,
    "p99_latency": 9586.717780516803,
    "violation_rate": 0.0403,
    "solver_runtime_sec": 26.107239666998794,
    "wall_time_sec": 56.987525083000946,
    "max_rss_mb": 1329.65625,
    "num_iterations": 3,
    "active_scenario_count": 6000,
    "active_scenario_fraction": 0.3,
    "assignment_signature": "[[\"Q/A\", \"q_a_aws_us-east-2_q2\"], [\"Shot Detection\", \"shot_detection_aliyun_cn-shanghai_q2\"], [\"Video Caption\", \"video_caption_aws_us-east-2_q2\"], [\"Video Split & Sample\", \"video_split_and_sample_aliyun_cn-shanghai_q2\"]]",
    "error": "",
    "process_exitcode": 0
  },
  {
    "workflow": "workflow1",
    "quality_level": "Q2",
    "query_count": 600,
    "eta": 0.1,
    "calibration_scenarios_per_query": 50,
    "test_scenarios_per_query": NaN,
    "calibration_scenario_count": 30000,
    "test_scenario_count": NaN,
    "method": "full_milp",
    "solver_method": "",
    "status": "FAILED",
    "reused_last_feasible": false,
    "objective_value": NaN,
    "expected_cost": NaN,
    "avg_latency": NaN,
    "p95_latency": NaN,
    "p99_latency": NaN,
    "violation_rate": NaN,
    "solver_runtime_sec": NaN,
    "wall_time_sec": 188.09137791600006,
    "max_rss_mb": 2826.78125,
    "num_iterations": 0,
    "active_scenario_count": 0,
    "active_scenario_fraction": NaN,
    "assignment_signature": "",
    "error": "RuntimeError: Full MILP failed to find a solution (status=INFEASIBLE)\nTraceback (most recent call last):\n  File \"/Users/heng/Documents/skybridge/sim/scripts/run_q_scaling_full_decomp_minp95.py\", line 89, in _worker\n    result = solve_full_milp(\n        workflow,\n    ...<4 lines>...\n        config,\n    )\n  File \"/Users/heng/Documents/skybridge/sim/src/milp_full.py\", line 50, in solve_full_milp\n    raise RuntimeError(f\"Full MILP failed to find a solution (status={status})\")\nRuntimeError: Full MILP failed to find a solution (status=INFEASIBLE)\n",
    "process_exitcode": 0
  },
  {
    "workflow": "workflow1",
    "quality_level": "Q2",
    "query_count": 600,
    "eta": 0.1,
    "calibration_scenarios_per_query": 50,
    "test_scenarios_per_query": 50,
    "calibration_scenario_count": 30000,
    "test_scenario_count": 30000,
    "method": "decomposed_milp",
    "solver_method": "decomposition",
    "status": "INFEASIBLE_REUSED_LAST_FEASIBLE",
    "reused_last_feasible": true,
    "objective_value": Infinity,
    "expected_cost": 2.7966600546255855,
    "avg_latency": 2272.397633138623,
    "p95_latency": 6694.5942955375795,
    "p99_latency": 11343.401185823624,
    "violation_rate": 0.06573333333333334,
    "solver_runtime_sec": 34.62437158300236,
    "wall_time_sec": 64.79304012500143,
    "max_rss_mb": 1405.21875,
    "num_iterations": 2,
    "active_scenario_count": 7500,
    "active_scenario_fraction": 0.25,
    "assignment_signature": "[[\"Q/A\", \"q_a_azure_eastus_q2\"], [\"Shot Detection\", \"shot_detection_aliyun_cn-shanghai_q2\"], [\"Video Caption\", \"video_caption_azure_eastus_q2\"], [\"Video Split & Sample\", \"video_split_and_sample_aliyun_cn-shanghai_q2\"]]",
    "error": "",
    "process_exitcode": 0
  },
  {
    "workflow": "workflow1",
    "quality_level": "Q2",
    "query_count": 800,
    "eta": 0.1,
    "calibration_scenarios_per_query": 50,
    "test_scenarios_per_query": NaN,
    "calibration_scenario_count": 40000,
    "test_scenario_count": NaN,
    "method": "full_milp",
    "solver_method": "",
    "status": "FAILED",
    "reused_last_feasible": false,
    "objective_value": NaN,
    "expected_cost": NaN,
    "avg_latency": NaN,
    "p95_latency": NaN,
    "p99_latency": NaN,
    "violation_rate": NaN,
    "solver_runtime_sec": NaN,
    "wall_time_sec": 367.1790257499997,
    "max_rss_mb": 3690.796875,
    "num_iterations": 0,
    "active_scenario_count": 0,
    "active_scenario_fraction": NaN,
    "assignment_signature": "",
    "error": "RuntimeError: Full MILP failed to find a solution (status=INFEASIBLE)\nTraceback (most recent call last):\n  File \"/Users/heng/Documents/skybridge/sim/scripts/run_q_scaling_full_decomp_minp95.py\", line 89, in _worker\n    result = solve_full_milp(\n        workflow,\n    ...<4 lines>...\n        config,\n    )\n  File \"/Users/heng/Documents/skybridge/sim/src/milp_full.py\", line 50, in solve_full_milp\n    raise RuntimeError(f\"Full MILP failed to find a solution (status={status})\")\nRuntimeError: Full MILP failed to find a solution (status=INFEASIBLE)\n",
    "process_exitcode": 0
  },
  {
    "workflow": "workflow1",
    "quality_level": "Q2",
    "query_count": 800,
    "eta": 0.1,
    "calibration_scenarios_per_query": 50,
    "test_scenarios_per_query": 50,
    "calibration_scenario_count": 40000,
    "test_scenario_count": 40000,
    "method": "decomposed_milp",
    "solver_method": "decomposition",
    "status": "INFEASIBLE_REUSED_LAST_FEASIBLE",
    "reused_last_feasible": true,
    "objective_value": Infinity,
    "expected_cost": 2.7731766645151663,
    "avg_latency": 2255.1074845453904,
    "p95_latency": 6651.505281916937,
    "p99_latency": 11252.701246208966,
    "violation_rate": 0.066075,
    "solver_runtime_sec": 64.89626670799771,
    "wall_time_sec": 101.97659691700028,
    "max_rss_mb": 1634.484375,
    "num_iterations": 2,
    "active_scenario_count": 10000,
    "active_scenario_fraction": 0.25,
    "assignment_signature": "[[\"Q/A\", \"q_a_azure_eastus_q2\"], [\"Shot Detection\", \"shot_detection_aliyun_cn-shanghai_q2\"], [\"Video Caption\", \"video_caption_azure_eastus_q2\"], [\"Video Split & Sample\", \"video_split_and_sample_aliyun_cn-shanghai_q2\"]]",
    "error": "",
    "process_exitcode": 0
  },
  {
    "workflow": "workflow1",
    "quality_level": "Q2",
    "query_count": 1000,
    "eta": 0.1,
    "calibration_scenarios_per_query": 50,
    "test_scenarios_per_query": NaN,
    "calibration_scenario_count": 50000,
    "test_scenario_count": NaN,
    "method": "full_milp",
    "solver_method": "",
    "status": "FAILED",
    "reused_last_feasible": false,
    "objective_value": NaN,
    "expected_cost": NaN,
    "avg_latency": NaN,
    "p95_latency": NaN,
    "p99_latency": NaN,
    "violation_rate": NaN,
    "solver_runtime_sec": NaN,
    "wall_time_sec": 348.0973802920016,
    "max_rss_mb": 4327.0,
    "num_iterations": 0,
    "active_scenario_count": 0,
    "active_scenario_fraction": NaN,
    "assignment_signature": "",
    "error": "RuntimeError: Full MILP failed to find a solution (status=TIME_LIMIT)\nTraceback (most recent call last):\n  File \"/Users/heng/Documents/skybridge/sim/scripts/run_q_scaling_full_decomp_minp95.py\", line 89, in _worker\n    result = solve_full_milp(\n        workflow,\n    ...<4 lines>...\n        config,\n    )\n  File \"/Users/heng/Documents/skybridge/sim/src/milp_full.py\", line 50, in solve_full_milp\n    raise RuntimeError(f\"Full MILP failed to find a solution (status={status})\")\nRuntimeError: Full MILP failed to find a solution (status=TIME_LIMIT)\n",
    "process_exitcode": 0
  },
  {
    "workflow": "workflow1",
    "quality_level": "Q2",
    "query_count": 1000,
    "eta": 0.1,
    "calibration_scenarios_per_query": 50,
    "test_scenarios_per_query": 50,
    "calibration_scenario_count": 50000,
    "test_scenario_count": 50000,
    "method": "decomposed_milp",
    "solver_method": "decomposition",
    "status": "INFEASIBLE_REUSED_LAST_FEASIBLE",
    "reused_last_feasible": true,
    "objective_value": Infinity,
    "expected_cost": 2.8338120419615924,
    "avg_latency": 2304.1140592025663,
    "p95_latency": 6687.79038237684,
    "p99_latency": 11380.364880108951,
    "violation_rate": 0.06676,
    "solver_runtime_sec": 88.11267325000154,
    "wall_time_sec": 132.66260370800228,
    "max_rss_mb": 1909.46875,
    "num_iterations": 2,
    "active_scenario_count": 12500,
    "active_scenario_fraction": 0.25,
    "assignment_signature": "[[\"Q/A\", \"q_a_azure_eastus_q2\"], [\"Shot Detection\", \"shot_detection_aliyun_cn-shanghai_q2\"], [\"Video Caption\", \"video_caption_azure_eastus_q2\"], [\"Video Split & Sample\", \"video_split_and_sample_aliyun_cn-shanghai_q2\"]]",
    "error": "",
    "process_exitcode": 0
  },
  {
    "workflow": "workflow1",
    "quality_level": "Q2",
    "query_count": 1200,
    "eta": 0.1,
    "calibration_scenarios_per_query": 50,
    "test_scenarios_per_query": NaN,
    "calibration_scenario_count": 60000,
    "test_scenario_count": NaN,
    "method": "full_milp",
    "solver_method": "",
    "status": "FAILED",
    "reused_last_feasible": false,
    "objective_value": NaN,
    "expected_cost": NaN,
    "avg_latency": NaN,
    "p95_latency": NaN,
    "p99_latency": NaN,
    "violation_rate": NaN,
    "solver_runtime_sec": NaN,
    "wall_time_sec": 494.30656400000225,
    "max_rss_mb": 3888.484375,
    "num_iterations": 0,
    "active_scenario_count": 0,
    "active_scenario_fraction": NaN,
    "assignment_signature": "",
    "error": "RuntimeError: Full MILP failed to find a solution (status=TIME_LIMIT)\nTraceback (most recent call last):\n  File \"/Users/heng/Documents/skybridge/sim/scripts/run_q_scaling_full_decomp_minp95.py\", line 89, in _worker\n    result = solve_full_milp(\n        workflow,\n    ...<4 lines>...\n        config,\n    )\n  File \"/Users/heng/Documents/skybridge/sim/src/milp_full.py\", line 50, in solve_full_milp\n    raise RuntimeError(f\"Full MILP failed to find a solution (status={status})\")\nRuntimeError: Full MILP failed to find a solution (status=TIME_LIMIT)\n",
    "process_exitcode": 0
  },
  {
    "workflow": "workflow1",
    "quality_level": "Q2",
    "query_count": 1200,
    "eta": 0.1,
    "calibration_scenarios_per_query": 50,
    "test_scenarios_per_query": 50,
    "calibration_scenario_count": 60000,
    "test_scenario_count": 60000,
    "method": "decomposed_milp",
    "solver_method": "decomposition",
    "status": "INFEASIBLE_REUSED_LAST_FEASIBLE",
    "reused_last_feasible": true,
    "objective_value": Infinity,
    "expected_cost": 2.821037743406051,
    "avg_latency": 2294.337035557492,
    "p95_latency": 6662.8366438151015,
    "p99_latency": 11386.461703975883,
    "violation_rate": 0.06683333333333333,
    "solver_runtime_sec": 149.05919479199656,
    "wall_time_sec": 199.2296631249992,
    "max_rss_mb": 2162.96875,
    "num_iterations": 2,
    "active_scenario_count": 15000,
    "active_scenario_fraction": 0.25,
    "assignment_signature": "[[\"Q/A\", \"q_a_azure_eastus_q2\"], [\"Shot Detection\", \"shot_detection_aliyun_cn-shanghai_q2\"], [\"Video Caption\", \"video_caption_azure_eastus_q2\"], [\"Video Split & Sample\", \"video_split_and_sample_aliyun_cn-shanghai_q2\"]]",
    "error": "",
    "process_exitcode": 0
  },
  {
    "workflow": "workflow1",
    "quality_level": "Q2",
    "query_count": 1400,
    "eta": 0.1,
    "calibration_scenarios_per_query": 50,
    "test_scenarios_per_query": NaN,
    "calibration_scenario_count": 70000,
    "test_scenario_count": NaN,
    "method": "full_milp",
    "solver_method": "",
    "status": "FAILED",
    "reused_last_feasible": false,
    "objective_value": NaN,
    "expected_cost": NaN,
    "avg_latency": NaN,
    "p95_latency": NaN,
    "p99_latency": NaN,
    "violation_rate": NaN,
    "solver_runtime_sec": NaN,
    "wall_time_sec": 407.2172920410012,
    "max_rss_mb": 5840.9375,
    "num_iterations": 0,
    "active_scenario_count": 0,
    "active_scenario_fraction": NaN,
    "assignment_signature": "",
    "error": "RuntimeError: Full MILP failed to find a solution (status=TIME_LIMIT)\nTraceback (most recent call last):\n  File \"/Users/heng/Documents/skybridge/sim/scripts/run_q_scaling_full_decomp_minp95.py\", line 89, in _worker\n    result = solve_full_milp(\n        workflow,\n    ...<4 lines>...\n        config,\n    )\n  File \"/Users/heng/Documents/skybridge/sim/src/milp_full.py\", line 50, in solve_full_milp\n    raise RuntimeError(f\"Full MILP failed to find a solution (status={status})\")\nRuntimeError: Full MILP failed to find a solution (status=TIME_LIMIT)\n",
    "process_exitcode": 0
  },
  {
    "workflow": "workflow1",
    "quality_level": "Q2",
    "query_count": 1400,
    "eta": 0.1,
    "calibration_scenarios_per_query": 50,
    "test_scenarios_per_query": 50,
    "calibration_scenario_count": 70000,
    "test_scenario_count": 70000,
    "method": "decomposed_milp",
    "solver_method": "decomposition",
    "status": "INFEASIBLE_REUSED_LAST_FEASIBLE",
    "reused_last_feasible": true,
    "objective_value": Infinity,
    "expected_cost": 2.8157781771209582,
    "avg_latency": 2289.020897343482,
    "p95_latency": 6638.8444207176,
    "p99_latency": 11380.364880108908,
    "violation_rate": 0.06664285714285714,
    "solver_runtime_sec": 211.18947791600294,
    "wall_time_sec": 267.81432558400047,
    "max_rss_mb": 2402.265625,
    "num_iterations": 2,
    "active_scenario_count": 17500,
    "active_scenario_fraction": 0.25,
    "assignment_signature": "[[\"Q/A\", \"q_a_azure_eastus_q2\"], [\"Shot Detection\", \"shot_detection_aliyun_cn-shanghai_q2\"], [\"Video Caption\", \"video_caption_azure_eastus_q2\"], [\"Video Split & Sample\", \"video_split_and_sample_aliyun_cn-shanghai_q2\"]]",
    "error": "",
    "process_exitcode": 0
  },
  {
    "workflow": "workflow1",
    "quality_level": "Q2",
    "query_count": 1600,
    "eta": 0.1,
    "calibration_scenarios_per_query": 50,
    "test_scenarios_per_query": NaN,
    "calibration_scenario_count": 80000,
    "test_scenario_count": NaN,
    "method": "full_milp",
    "solver_method": "",
    "status": "FAILED",
    "reused_last_feasible": false,
    "objective_value": NaN,
    "expected_cost": NaN,
    "avg_latency": NaN,
    "p95_latency": NaN,
    "p99_latency": NaN,
    "violation_rate": NaN,
    "solver_runtime_sec": NaN,
    "wall_time_sec": 268.55598033299975,
    "max_rss_mb": 6415.953125,
    "num_iterations": 0,
    "active_scenario_count": 0,
    "active_scenario_fraction": NaN,
    "assignment_signature": "",
    "error": "RuntimeError: Full MILP failed to find a solution (status=INFEASIBLE)\nTraceback (most recent call last):\n  File \"/Users/heng/Documents/skybridge/sim/scripts/run_q_scaling_full_decomp_minp95.py\", line 89, in _worker\n    result = solve_full_milp(\n        workflow,\n    ...<4 lines>...\n        config,\n    )\n  File \"/Users/heng/Documents/skybridge/sim/src/milp_full.py\", line 50, in solve_full_milp\n    raise RuntimeError(f\"Full MILP failed to find a solution (status={status})\")\nRuntimeError: Full MILP failed to find a solution (status=INFEASIBLE)\n",
    "process_exitcode": 0
  },
  {
    "workflow": "workflow1",
    "quality_level": "Q2",
    "query_count": 1600,
    "eta": 0.1,
    "calibration_scenarios_per_query": 50,
    "test_scenarios_per_query": 50,
    "calibration_scenario_count": 80000,
    "test_scenario_count": 80000,
    "method": "decomposed_milp",
    "solver_method": "decomposition",
    "status": "INFEASIBLE_REUSED_LAST_FEASIBLE",
    "reused_last_feasible": true,
    "objective_value": Infinity,
    "expected_cost": 2.8028939187077246,
    "avg_latency": 2277.8433459831626,
    "p95_latency": 6613.614326908204,
    "p99_latency": 11335.492302645373,
    "violation_rate": 0.06645,
    "solver_runtime_sec": 104.68932133299677,
    "wall_time_sec": 168.81268091699894,
    "max_rss_mb": 2669.9375,
    "num_iterations": 2,
    "active_scenario_count": 20000,
    "active_scenario_fraction": 0.25,
    "assignment_signature": "[[\"Q/A\", \"q_a_azure_eastus_q2\"], [\"Shot Detection\", \"shot_detection_aliyun_cn-shanghai_q2\"], [\"Video Caption\", \"video_caption_azure_eastus_q2\"], [\"Video Split & Sample\", \"video_split_and_sample_aliyun_cn-shanghai_q2\"]]",
    "error": "",
    "process_exitcode": 0
  },
  {
    "workflow": "workflow1",
    "quality_level": "Q2",
    "query_count": 1800,
    "eta": 0.1,
    "calibration_scenarios_per_query": 50,
    "test_scenarios_per_query": NaN,
    "calibration_scenario_count": 90000,
    "test_scenario_count": NaN,
    "method": "full_milp",
    "solver_method": "",
    "status": "FAILED",
    "reused_last_feasible": false,
    "objective_value": NaN,
    "expected_cost": NaN,
    "avg_latency": NaN,
    "p95_latency": NaN,
    "p99_latency": NaN,
    "violation_rate": NaN,
    "solver_runtime_sec": NaN,
    "wall_time_sec": 654.2469735410014,
    "max_rss_mb": 6677.0625,
    "num_iterations": 0,
    "active_scenario_count": 0,
    "active_scenario_fraction": NaN,
    "assignment_signature": "",
    "error": "RuntimeError: Full MILP failed to find a solution (status=TIME_LIMIT)\nTraceback (most recent call last):\n  File \"/Users/heng/Documents/skybridge/sim/scripts/run_q_scaling_full_decomp_minp95.py\", line 89, in _worker\n    result = solve_full_milp(\n        workflow,\n    ...<4 lines>...\n        config,\n    )\n  File \"/Users/heng/Documents/skybridge/sim/src/milp_full.py\", line 50, in solve_full_milp\n    raise RuntimeError(f\"Full MILP failed to find a solution (status={status})\")\nRuntimeError: Full MILP failed to find a solution (status=TIME_LIMIT)\n",
    "process_exitcode": 0
  },
  {
    "workflow": "workflow1",
    "quality_level": "Q2",
    "query_count": 1800,
    "eta": 0.1,
    "calibration_scenarios_per_query": 50,
    "test_scenarios_per_query": 50,
    "calibration_scenario_count": 90000,
    "test_scenario_count": 90000,
    "method": "decomposed_milp",
    "solver_method": "decomposition",
    "status": "INFEASIBLE_REUSED_LAST_FEASIBLE",
    "reused_last_feasible": true,
    "objective_value": Infinity,
    "expected_cost": 2.811616292295103,
    "avg_latency": 2284.355984214801,
    "p95_latency": 6634.612304209423,
    "p99_latency": 11317.206821098609,
    "violation_rate": 0.06652222222222222,
    "solver_runtime_sec": 337.8996070420035,
    "wall_time_sec": 408.8475580410013,
    "max_rss_mb": 2921.5,
    "num_iterations": 2,
    "active_scenario_count": 22500,
    "active_scenario_fraction": 0.25,
    "assignment_signature": "[[\"Q/A\", \"q_a_azure_eastus_q2\"], [\"Shot Detection\", \"shot_detection_aliyun_cn-shanghai_q2\"], [\"Video Caption\", \"video_caption_azure_eastus_q2\"], [\"Video Split & Sample\", \"video_split_and_sample_aliyun_cn-shanghai_q2\"]]",
    "error": "",
    "process_exitcode": 0
  },
  {
    "workflow": "workflow1",
    "quality_level": "Q2",
    "query_count": 2000,
    "eta": 0.1,
    "calibration_scenarios_per_query": 50,
    "test_scenarios_per_query": NaN,
    "calibration_scenario_count": 100000,
    "test_scenario_count": NaN,
    "method": "full_milp",
    "solver_method": "",
    "status": "FAILED",
    "reused_last_feasible": false,
    "objective_value": NaN,
    "expected_cost": NaN,
    "avg_latency": NaN,
    "p95_latency": NaN,
    "p99_latency": NaN,
    "violation_rate": NaN,
    "solver_runtime_sec": NaN,
    "wall_time_sec": 771.986050083,
    "max_rss_mb": 6757.765625,
    "num_iterations": 0,
    "active_scenario_count": 0,
    "active_scenario_fraction": NaN,
    "assignment_signature": "",
    "error": "RuntimeError: Full MILP failed to find a solution (status=TIME_LIMIT)\nTraceback (most recent call last):\n  File \"/Users/heng/Documents/skybridge/sim/scripts/run_q_scaling_full_decomp_minp95.py\", line 89, in _worker\n    result = solve_full_milp(\n        workflow,\n    ...<4 lines>...\n        config,\n    )\n  File \"/Users/heng/Documents/skybridge/sim/src/milp_full.py\", line 50, in solve_full_milp\n    raise RuntimeError(f\"Full MILP failed to find a solution (status={status})\")\nRuntimeError: Full MILP failed to find a solution (status=TIME_LIMIT)\n",
    "process_exitcode": 0
  },
  {
    "workflow": "workflow1",
    "quality_level": "Q2",
    "query_count": 2000,
    "eta": 0.1,
    "calibration_scenarios_per_query": 50,
    "test_scenarios_per_query": 50,
    "calibration_scenario_count": 100000,
    "test_scenario_count": 100000,
    "method": "decomposed_milp",
    "solver_method": "decomposition",
    "status": "INFEASIBLE_REUSED_LAST_FEASIBLE",
    "reused_last_feasible": true,
    "objective_value": Infinity,
    "expected_cost": 2.8040150863835613,
    "avg_latency": 2278.9129701844627,
    "p95_latency": 6625.603359305095,
    "p99_latency": 11319.303294335568,
    "violation_rate": 0.06686,
    "solver_runtime_sec": 409.7528150829967,
    "wall_time_sec": 487.8024682079995,
    "max_rss_mb": 3194.671875,
    "num_iterations": 2,
    "active_scenario_count": 25000,
    "active_scenario_fraction": 0.25,
    "assignment_signature": "[[\"Q/A\", \"q_a_azure_eastus_q2\"], [\"Shot Detection\", \"shot_detection_aliyun_cn-shanghai_q2\"], [\"Video Caption\", \"video_caption_azure_eastus_q2\"], [\"Video Split & Sample\", \"video_split_and_sample_aliyun_cn-shanghai_q2\"]]",
    "error": "",
    "process_exitcode": 0
  },
  {
    "workflow": "workflow1",
    "quality_level": "Q3",
    "query_count": 200,
    "eta": 0.1,
    "calibration_scenarios_per_query": 50,
    "test_scenarios_per_query": NaN,
    "calibration_scenario_count": 10000,
    "test_scenario_count": NaN,
    "method": "full_milp",
    "solver_method": "",
    "status": "FAILED",
    "reused_last_feasible": false,
    "objective_value": NaN,
    "expected_cost": NaN,
    "avg_latency": NaN,
    "p95_latency": NaN,
    "p99_latency": NaN,
    "violation_rate": NaN,
    "solver_runtime_sec": NaN,
    "wall_time_sec": 19.997451166000246,
    "max_rss_mb": 1242.734375,
    "num_iterations": 0,
    "active_scenario_count": 0,
    "active_scenario_fraction": NaN,
    "assignment_signature": "",
    "error": "RuntimeError: Full MILP failed to find a solution (status=INFEASIBLE)\nTraceback (most recent call last):\n  File \"/Users/heng/Documents/skybridge/sim/scripts/run_q_scaling_full_decomp_minp95.py\", line 89, in _worker\n    result = solve_full_milp(\n        workflow,\n    ...<4 lines>...\n        config,\n    )\n  File \"/Users/heng/Documents/skybridge/sim/src/milp_full.py\", line 50, in solve_full_milp\n    raise RuntimeError(f\"Full MILP failed to find a solution (status={status})\")\nRuntimeError: Full MILP failed to find a solution (status=INFEASIBLE)\n",
    "process_exitcode": 0
  },
  {
    "workflow": "workflow1",
    "quality_level": "Q3",
    "query_count": 200,
    "eta": 0.1,
    "calibration_scenarios_per_query": 50,
    "test_scenarios_per_query": 50,
    "calibration_scenario_count": 10000,
    "test_scenario_count": 10000,
    "method": "decomposed_milp",
    "solver_method": "decomposition",
    "status": "INFEASIBLE_REUSED_LAST_FEASIBLE",
    "reused_last_feasible": true,
    "objective_value": Infinity,
    "expected_cost": 6.7860712928060645,
    "avg_latency": 3855.2753857573653,
    "p95_latency": 11041.867503008194,
    "p99_latency": 19626.92307306333,
    "violation_rate": 0.0673,
    "solver_runtime_sec": 4.464092666999932,
    "wall_time_sec": 20.99648150000212,
    "max_rss_mb": 1130.265625,
    "num_iterations": 2,
    "active_scenario_count": 2500,
    "active_scenario_fraction": 0.25,
    "assignment_signature": "[[\"Q/A\", \"q_a_azure_eastus_q3\"], [\"Shot Detection\", \"shot_detection_aliyun_cn-shanghai_q3\"], [\"Video Caption\", \"video_caption_azure_eastus_q3\"], [\"Video Split & Sample\", \"video_split_and_sample_aliyun_cn-shanghai_q3\"]]",
    "error": "",
    "process_exitcode": 0
  },
  {
    "workflow": "workflow1",
    "quality_level": "Q3",
    "query_count": 400,
    "eta": 0.1,
    "calibration_scenarios_per_query": 50,
    "test_scenarios_per_query": NaN,
    "calibration_scenario_count": 20000,
    "test_scenario_count": NaN,
    "method": "full_milp",
    "solver_method": "",
    "status": "FAILED",
    "reused_last_feasible": false,
    "objective_value": NaN,
    "expected_cost": NaN,
    "avg_latency": NaN,
    "p95_latency": NaN,
    "p99_latency": NaN,
    "violation_rate": NaN,
    "solver_runtime_sec": NaN,
    "wall_time_sec": 115.82134429099824,
    "max_rss_mb": 2070.484375,
    "num_iterations": 0,
    "active_scenario_count": 0,
    "active_scenario_fraction": NaN,
    "assignment_signature": "",
    "error": "RuntimeError: Full MILP failed to find a solution (status=INFEASIBLE)\nTraceback (most recent call last):\n  File \"/Users/heng/Documents/skybridge/sim/scripts/run_q_scaling_full_decomp_minp95.py\", line 89, in _worker\n    result = solve_full_milp(\n        workflow,\n    ...<4 lines>...\n        config,\n    )\n  File \"/Users/heng/Documents/skybridge/sim/src/milp_full.py\", line 50, in solve_full_milp\n    raise RuntimeError(f\"Full MILP failed to find a solution (status={status})\")\nRuntimeError: Full MILP failed to find a solution (status=INFEASIBLE)\n",
    "process_exitcode": 0
  },
  {
    "workflow": "workflow1",
    "quality_level": "Q3",
    "query_count": 400,
    "eta": 0.1,
    "calibration_scenarios_per_query": 50,
    "test_scenarios_per_query": 50,
    "calibration_scenario_count": 20000,
    "test_scenario_count": 20000,
    "method": "decomposed_milp",
    "solver_method": "decomposition",
    "status": "INFEASIBLE_REUSED_LAST_FEASIBLE",
    "reused_last_feasible": true,
    "objective_value": Infinity,
    "expected_cost": 6.843020343494852,
    "avg_latency": 3887.9326481779017,
    "p95_latency": 10994.259292550803,
    "p99_latency": 19331.535420675664,
    "violation_rate": 0.06775,
    "solver_runtime_sec": 18.516189750000194,
    "wall_time_sec": 42.039918375001434,
    "max_rss_mb": 1192.984375,
    "num_iterations": 2,
    "active_scenario_count": 5000,
    "active_scenario_fraction": 0.25,
    "assignment_signature": "[[\"Q/A\", \"q_a_azure_eastus_q3\"], [\"Shot Detection\", \"shot_detection_aliyun_cn-shanghai_q3\"], [\"Video Caption\", \"video_caption_azure_eastus_q3\"], [\"Video Split & Sample\", \"video_split_and_sample_aliyun_cn-shanghai_q3\"]]",
    "error": "",
    "process_exitcode": 0
  },
  {
    "workflow": "workflow1",
    "quality_level": "Q3",
    "query_count": 600,
    "eta": 0.1,
    "calibration_scenarios_per_query": 50,
    "test_scenarios_per_query": NaN,
    "calibration_scenario_count": 30000,
    "test_scenario_count": NaN,
    "method": "full_milp",
    "solver_method": "",
    "status": "FAILED",
    "reused_last_feasible": false,
    "objective_value": NaN,
    "expected_cost": NaN,
    "avg_latency": NaN,
    "p95_latency": NaN,
    "p99_latency": NaN,
    "violation_rate": NaN,
    "solver_runtime_sec": NaN,
    "wall_time_sec": 261.895005958002,
    "max_rss_mb": 2862.984375,
    "num_iterations": 0,
    "active_scenario_count": 0,
    "active_scenario_fraction": NaN,
    "assignment_signature": "",
    "error": "RuntimeError: Full MILP failed to find a solution (status=INFEASIBLE)\nTraceback (most recent call last):\n  File \"/Users/heng/Documents/skybridge/sim/scripts/run_q_scaling_full_decomp_minp95.py\", line 89, in _worker\n    result = solve_full_milp(\n        workflow,\n    ...<4 lines>...\n        config,\n    )\n  File \"/Users/heng/Documents/skybridge/sim/src/milp_full.py\", line 50, in solve_full_milp\n    raise RuntimeError(f\"Full MILP failed to find a solution (status={status})\")\nRuntimeError: Full MILP failed to find a solution (status=INFEASIBLE)\n",
    "process_exitcode": 0
  },
  {
    "workflow": "workflow1",
    "quality_level": "Q3",
    "query_count": 600,
    "eta": 0.1,
    "calibration_scenarios_per_query": 50,
    "test_scenarios_per_query": 50,
    "calibration_scenario_count": 30000,
    "test_scenario_count": 30000,
    "method": "decomposed_milp",
    "solver_method": "decomposition",
    "status": "INFEASIBLE_REUSED_LAST_FEASIBLE",
    "reused_last_feasible": true,
    "objective_value": Infinity,
    "expected_cost": 6.728677572208421,
    "avg_latency": 3823.217814954578,
    "p95_latency": 10953.351447978024,
    "p99_latency": 19309.504475123453,
    "violation_rate": 0.06653333333333333,
    "solver_runtime_sec": 37.57474787599858,
    "wall_time_sec": 67.36117195800034,
    "max_rss_mb": 1352.625,
    "num_iterations": 2,
    "active_scenario_count": 7500,
    "active_scenario_fraction": 0.25,
    "assignment_signature": "[[\"Q/A\", \"q_a_azure_eastus_q3\"], [\"Shot Detection\", \"shot_detection_aliyun_cn-shanghai_q3\"], [\"Video Caption\", \"video_caption_azure_eastus_q3\"], [\"Video Split & Sample\", \"video_split_and_sample_aliyun_cn-shanghai_q3\"]]",
    "error": "",
    "process_exitcode": 0
  },
  {
    "workflow": "workflow1",
    "quality_level": "Q3",
    "query_count": 800,
    "eta": 0.1,
    "calibration_scenarios_per_query": 50,
    "test_scenarios_per_query": NaN,
    "calibration_scenario_count": 40000,
    "test_scenario_count": NaN,
    "method": "full_milp",
    "solver_method": "",
    "status": "FAILED",
    "reused_last_feasible": false,
    "objective_value": NaN,
    "expected_cost": NaN,
    "avg_latency": NaN,
    "p95_latency": NaN,
    "p99_latency": NaN,
    "violation_rate": NaN,
    "solver_runtime_sec": NaN,
    "wall_time_sec": 338.9183997909968,
    "max_rss_mb": 3559.46875,
    "num_iterations": 0,
    "active_scenario_count": 0,
    "active_scenario_fraction": NaN,
    "assignment_signature": "",
    "error": "RuntimeError: Full MILP failed to find a solution (status=TIME_LIMIT)\nTraceback (most recent call last):\n  File \"/Users/heng/Documents/skybridge/sim/scripts/run_q_scaling_full_decomp_minp95.py\", line 89, in _worker\n    result = solve_full_milp(\n        workflow,\n    ...<4 lines>...\n        config,\n    )\n  File \"/Users/heng/Documents/skybridge/sim/src/milp_full.py\", line 50, in solve_full_milp\n    raise RuntimeError(f\"Full MILP failed to find a solution (status={status})\")\nRuntimeError: Full MILP failed to find a solution (status=TIME_LIMIT)\n",
    "process_exitcode": 0
  },
  {
    "workflow": "workflow1",
    "quality_level": "Q3",
    "query_count": 800,
    "eta": 0.1,
    "calibration_scenarios_per_query": 50,
    "test_scenarios_per_query": 50,
    "calibration_scenario_count": 40000,
    "test_scenario_count": 40000,
    "method": "decomposed_milp",
    "solver_method": "decomposition",
    "status": "INFEASIBLE_REUSED_LAST_FEASIBLE",
    "reused_last_feasible": true,
    "objective_value": Infinity,
    "expected_cost": 6.899910989880995,
    "avg_latency": 3920.813915009328,
    "p95_latency": 11202.949656600373,
    "p99_latency": 19859.84966070415,
    "violation_rate": 0.06595,
    "solver_runtime_sec": 70.12720949900176,
    "wall_time_sec": 107.15471633400011,
    "max_rss_mb": 1597.65625,
    "num_iterations": 2,
    "active_scenario_count": 10000,
    "active_scenario_fraction": 0.25,
    "assignment_signature": "[[\"Q/A\", \"q_a_azure_eastus_q3\"], [\"Shot Detection\", \"shot_detection_aliyun_cn-shanghai_q3\"], [\"Video Caption\", \"video_caption_azure_eastus_q3\"], [\"Video Split & Sample\", \"video_split_and_sample_aliyun_cn-shanghai_q3\"]]",
    "error": "",
    "process_exitcode": 0
  },
  {
    "workflow": "workflow1",
    "quality_level": "Q3",
    "query_count": 1000,
    "eta": 0.1,
    "calibration_scenarios_per_query": 50,
    "test_scenarios_per_query": NaN,
    "calibration_scenario_count": 50000,
    "test_scenario_count": NaN,
    "method": "full_milp",
    "solver_method": "",
    "status": "FAILED",
    "reused_last_feasible": false,
    "objective_value": NaN,
    "expected_cost": NaN,
    "avg_latency": NaN,
    "p95_latency": NaN,
    "p99_latency": NaN,
    "violation_rate": NaN,
    "solver_runtime_sec": NaN,
    "wall_time_sec": 378.8868516250004,
    "max_rss_mb": 4269.28125,
    "num_iterations": 0,
    "active_scenario_count": 0,
    "active_scenario_fraction": NaN,
    "assignment_signature": "",
    "error": "RuntimeError: Full MILP failed to find a solution (status=TIME_LIMIT)\nTraceback (most recent call last):\n  File \"/Users/heng/Documents/skybridge/sim/scripts/run_q_scaling_full_decomp_minp95.py\", line 89, in _worker\n    result = solve_full_milp(\n        workflow,\n    ...<4 lines>...\n        config,\n    )\n  File \"/Users/heng/Documents/skybridge/sim/src/milp_full.py\", line 50, in solve_full_milp\n    raise RuntimeError(f\"Full MILP failed to find a solution (status={status})\")\nRuntimeError: Full MILP failed to find a solution (status=TIME_LIMIT)\n",
    "process_exitcode": 0
  },
  {
    "workflow": "workflow1",
    "quality_level": "Q3",
    "query_count": 1000,
    "eta": 0.1,
    "calibration_scenarios_per_query": 50,
    "test_scenarios_per_query": 50,
    "calibration_scenario_count": 50000,
    "test_scenario_count": 50000,
    "method": "decomposed_milp",
    "solver_method": "decomposition",
    "status": "INFEASIBLE_REUSED_LAST_FEASIBLE",
    "reused_last_feasible": true,
    "objective_value": Infinity,
    "expected_cost": 6.89509967353863,
    "avg_latency": 3919.2489767757525,
    "p95_latency": 11274.446680512328,
    "p99_latency": 19777.303157671813,
    "violation_rate": 0.0657,
    "solver_runtime_sec": 109.03563058299915,
    "wall_time_sec": 152.72960462500123,
    "max_rss_mb": 1916.3125,
    "num_iterations": 2,
    "active_scenario_count": 12500,
    "active_scenario_fraction": 0.25,
    "assignment_signature": "[[\"Q/A\", \"q_a_azure_eastus_q3\"], [\"Shot Detection\", \"shot_detection_aliyun_cn-shanghai_q3\"], [\"Video Caption\", \"video_caption_azure_eastus_q3\"], [\"Video Split & Sample\", \"video_split_and_sample_aliyun_cn-shanghai_q3\"]]",
    "error": "",
    "process_exitcode": 0
  },
  {
    "workflow": "workflow1",
    "quality_level": "Q3",
    "query_count": 1200,
    "eta": 0.1,
    "calibration_scenarios_per_query": 50,
    "test_scenarios_per_query": NaN,
    "calibration_scenario_count": 60000,
    "test_scenario_count": NaN,
    "method": "full_milp",
    "solver_method": "",
    "status": "FAILED",
    "reused_last_feasible": false,
    "objective_value": NaN,
    "expected_cost": NaN,
    "avg_latency": NaN,
    "p95_latency": NaN,
    "p99_latency": NaN,
    "violation_rate": NaN,
    "solver_runtime_sec": NaN,
    "wall_time_sec": 424.51135870800135,
    "max_rss_mb": 5051.171875,
    "num_iterations": 0,
    "active_scenario_count": 0,
    "active_scenario_fraction": NaN,
    "assignment_signature": "",
    "error": "RuntimeError: Full MILP failed to find a solution (status=TIME_LIMIT)\nTraceback (most recent call last):\n  File \"/Users/heng/Documents/skybridge/sim/scripts/run_q_scaling_full_decomp_minp95.py\", line 89, in _worker\n    result = solve_full_milp(\n        workflow,\n    ...<4 lines>...\n        config,\n    )\n  File \"/Users/heng/Documents/skybridge/sim/src/milp_full.py\", line 50, in solve_full_milp\n    raise RuntimeError(f\"Full MILP failed to find a solution (status={status})\")\nRuntimeError: Full MILP failed to find a solution (status=TIME_LIMIT)\n",
    "process_exitcode": 0
  },
  {
    "workflow": "workflow1",
    "quality_level": "Q3",
    "query_count": 1200,
    "eta": 0.1,
    "calibration_scenarios_per_query": 50,
    "test_scenarios_per_query": 50,
    "calibration_scenario_count": 60000,
    "test_scenario_count": 60000,
    "method": "decomposed_milp",
    "solver_method": "decomposition",
    "status": "INFEASIBLE_REUSED_LAST_FEASIBLE",
    "reused_last_feasible": true,
    "objective_value": Infinity,
    "expected_cost": 6.969486390834034,
    "avg_latency": 3960.917356344681,
    "p95_latency": 11413.740271683162,
    "p99_latency": 20014.927201752154,
    "violation_rate": 0.06596666666666667,
    "solver_runtime_sec": 156.38219033399946,
    "wall_time_sec": 207.29366879200097,
    "max_rss_mb": 2094.328125,
    "num_iterations": 2,
    "active_scenario_count": 15000,
    "active_scenario_fraction": 0.25,
    "assignment_signature": "[[\"Q/A\", \"q_a_azure_eastus_q3\"], [\"Shot Detection\", \"shot_detection_aliyun_cn-shanghai_q3\"], [\"Video Caption\", \"video_caption_azure_eastus_q3\"], [\"Video Split & Sample\", \"video_split_and_sample_aliyun_cn-shanghai_q3\"]]",
    "error": "",
    "process_exitcode": 0
  },
  {
    "workflow": "workflow1",
    "quality_level": "Q3",
    "query_count": 1400,
    "eta": 0.1,
    "calibration_scenarios_per_query": 50,
    "test_scenarios_per_query": NaN,
    "calibration_scenario_count": 70000,
    "test_scenario_count": NaN,
    "method": "full_milp",
    "solver_method": "",
    "status": "FAILED",
    "reused_last_feasible": false,
    "objective_value": NaN,
    "expected_cost": NaN,
    "avg_latency": NaN,
    "p95_latency": NaN,
    "p99_latency": NaN,
    "violation_rate": NaN,
    "solver_runtime_sec": NaN,
    "wall_time_sec": 436.08700045799924,
    "max_rss_mb": 5585.390625,
    "num_iterations": 0,
    "active_scenario_count": 0,
    "active_scenario_fraction": NaN,
    "assignment_signature": "",
    "error": "RuntimeError: Full MILP failed to find a solution (status=TIME_LIMIT)\nTraceback (most recent call last):\n  File \"/Users/heng/Documents/skybridge/sim/scripts/run_q_scaling_full_decomp_minp95.py\", line 89, in _worker\n    result = solve_full_milp(\n        workflow,\n    ...<4 lines>...\n        config,\n    )\n  File \"/Users/heng/Documents/skybridge/sim/src/milp_full.py\", line 50, in solve_full_milp\n    raise RuntimeError(f\"Full MILP failed to find a solution (status={status})\")\nRuntimeError: Full MILP failed to find a solution (status=TIME_LIMIT)\n",
    "process_exitcode": 0
  },
  {
    "workflow": "workflow1",
    "quality_level": "Q3",
    "query_count": 1400,
    "eta": 0.1,
    "calibration_scenarios_per_query": 50,
    "test_scenarios_per_query": 50,
    "calibration_scenario_count": 70000,
    "test_scenario_count": 70000,
    "method": "decomposed_milp",
    "solver_method": "decomposition",
    "status": "INFEASIBLE_REUSED_LAST_FEASIBLE",
    "reused_last_feasible": true,
    "objective_value": Infinity,
    "expected_cost": 6.967906416388969,
    "avg_latency": 3959.7043209592307,
    "p95_latency": 11400.23708401212,
    "p99_latency": 19832.45257470346,
    "violation_rate": 0.06627142857142858,
    "solver_runtime_sec": 205.92622237600153,
    "wall_time_sec": 262.91332537500057,
    "max_rss_mb": 2409.9375,
    "num_iterations": 2,
    "active_scenario_count": 17500,
    "active_scenario_fraction": 0.25,
    "assignment_signature": "[[\"Q/A\", \"q_a_azure_eastus_q3\"], [\"Shot Detection\", \"shot_detection_aliyun_cn-shanghai_q3\"], [\"Video Caption\", \"video_caption_azure_eastus_q3\"], [\"Video Split & Sample\", \"video_split_and_sample_aliyun_cn-shanghai_q3\"]]",
    "error": "",
    "process_exitcode": 0
  },
  {
    "workflow": "workflow1",
    "quality_level": "Q3",
    "query_count": 1600,
    "eta": 0.1,
    "calibration_scenarios_per_query": 50,
    "test_scenarios_per_query": NaN,
    "calibration_scenario_count": 80000,
    "test_scenario_count": NaN,
    "method": "full_milp",
    "solver_method": "",
    "status": "FAILED",
    "reused_last_feasible": false,
    "objective_value": NaN,
    "expected_cost": NaN,
    "avg_latency": NaN,
    "p95_latency": NaN,
    "p99_latency": NaN,
    "violation_rate": NaN,
    "solver_runtime_sec": NaN,
    "wall_time_sec": 258.2239578330009,
    "max_rss_mb": 6317.21875,
    "num_iterations": 0,
    "active_scenario_count": 0,
    "active_scenario_fraction": NaN,
    "assignment_signature": "",
    "error": "RuntimeError: Full MILP failed to find a solution (status=INFEASIBLE)\nTraceback (most recent call last):\n  File \"/Users/heng/Documents/skybridge/sim/scripts/run_q_scaling_full_decomp_minp95.py\", line 89, in _worker\n    result = solve_full_milp(\n        workflow,\n    ...<4 lines>...\n        config,\n    )\n  File \"/Users/heng/Documents/skybridge/sim/src/milp_full.py\", line 50, in solve_full_milp\n    raise RuntimeError(f\"Full MILP failed to find a solution (status={status})\")\nRuntimeError: Full MILP failed to find a solution (status=INFEASIBLE)\n",
    "process_exitcode": 0
  },
  {
    "workflow": "workflow1",
    "quality_level": "Q3",
    "query_count": 1600,
    "eta": 0.1,
    "calibration_scenarios_per_query": 50,
    "test_scenarios_per_query": 50,
    "calibration_scenario_count": 80000,
    "test_scenario_count": 80000,
    "method": "decomposed_milp",
    "solver_method": "decomposition",
    "status": "INFEASIBLE_REUSED_LAST_FEASIBLE",
    "reused_last_feasible": true,
    "objective_value": Infinity,
    "expected_cost": 6.949080470535533,
    "avg_latency": 3948.951778383474,
    "p95_latency": 11384.694968845366,
    "p99_latency": 19763.219293175825,
    "violation_rate": 0.0659375,
    "solver_runtime_sec": 99.71856879199913,
    "wall_time_sec": 163.81432399999903,
    "max_rss_mb": 2666.046875,
    "num_iterations": 2,
    "active_scenario_count": 20000,
    "active_scenario_fraction": 0.25,
    "assignment_signature": "[[\"Q/A\", \"q_a_azure_eastus_q3\"], [\"Shot Detection\", \"shot_detection_aliyun_cn-shanghai_q3\"], [\"Video Caption\", \"video_caption_azure_eastus_q3\"], [\"Video Split & Sample\", \"video_split_and_sample_aliyun_cn-shanghai_q3\"]]",
    "error": "",
    "process_exitcode": 0
  },
  {
    "workflow": "workflow1",
    "quality_level": "Q3",
    "query_count": 1800,
    "eta": 0.1,
    "calibration_scenarios_per_query": 50,
    "test_scenarios_per_query": NaN,
    "calibration_scenario_count": 90000,
    "test_scenario_count": NaN,
    "method": "full_milp",
    "solver_method": "",
    "status": "FAILED",
    "reused_last_feasible": false,
    "objective_value": NaN,
    "expected_cost": NaN,
    "avg_latency": NaN,
    "p95_latency": NaN,
    "p99_latency": NaN,
    "violation_rate": NaN,
    "solver_runtime_sec": NaN,
    "wall_time_sec": 640.900378667,
    "max_rss_mb": 6615.0,
    "num_iterations": 0,
    "active_scenario_count": 0,
    "active_scenario_fraction": NaN,
    "assignment_signature": "",
    "error": "RuntimeError: Full MILP failed to find a solution (status=TIME_LIMIT)\nTraceback (most recent call last):\n  File \"/Users/heng/Documents/skybridge/sim/scripts/run_q_scaling_full_decomp_minp95.py\", line 89, in _worker\n    result = solve_full_milp(\n        workflow,\n    ...<4 lines>...\n        config,\n    )\n  File \"/Users/heng/Documents/skybridge/sim/src/milp_full.py\", line 50, in solve_full_milp\n    raise RuntimeError(f\"Full MILP failed to find a solution (status={status})\")\nRuntimeError: Full MILP failed to find a solution (status=TIME_LIMIT)\n",
    "process_exitcode": 0
  },
  {
    "workflow": "workflow1",
    "quality_level": "Q3",
    "query_count": 1800,
    "eta": 0.1,
    "calibration_scenarios_per_query": 50,
    "test_scenarios_per_query": 50,
    "calibration_scenario_count": 90000,
    "test_scenario_count": 90000,
    "method": "decomposed_milp",
    "solver_method": "decomposition",
    "status": "INFEASIBLE_REUSED_LAST_FEASIBLE",
    "reused_last_feasible": true,
    "objective_value": Infinity,
    "expected_cost": 6.950064287127099,
    "avg_latency": 3949.5545071093507,
    "p95_latency": 11360.15720554416,
    "p99_latency": 19732.79094632827,
    "violation_rate": 0.06574444444444444,
    "solver_runtime_sec": 335.3577341249984,
    "wall_time_sec": 406.61132291699687,
    "max_rss_mb": 2863.9375,
    "num_iterations": 2,
    "active_scenario_count": 22500,
    "active_scenario_fraction": 0.25,
    "assignment_signature": "[[\"Q/A\", \"q_a_azure_eastus_q3\"], [\"Shot Detection\", \"shot_detection_aliyun_cn-shanghai_q3\"], [\"Video Caption\", \"video_caption_azure_eastus_q3\"], [\"Video Split & Sample\", \"video_split_and_sample_aliyun_cn-shanghai_q3\"]]",
    "error": "",
    "process_exitcode": 0
  },
  {
    "workflow": "workflow1",
    "quality_level": "Q3",
    "query_count": 2000,
    "eta": 0.1,
    "calibration_scenarios_per_query": 50,
    "test_scenarios_per_query": NaN,
    "calibration_scenario_count": 100000,
    "test_scenario_count": NaN,
    "method": "full_milp",
    "solver_method": "",
    "status": "FAILED",
    "reused_last_feasible": false,
    "objective_value": NaN,
    "expected_cost": NaN,
    "avg_latency": NaN,
    "p95_latency": NaN,
    "p99_latency": NaN,
    "violation_rate": NaN,
    "solver_runtime_sec": NaN,
    "wall_time_sec": 784.0192290830018,
    "max_rss_mb": 6295.1875,
    "num_iterations": 0,
    "active_scenario_count": 0,
    "active_scenario_fraction": NaN,
    "assignment_signature": "",
    "error": "RuntimeError: Full MILP failed to find a solution (status=TIME_LIMIT)\nTraceback (most recent call last):\n  File \"/Users/heng/Documents/skybridge/sim/scripts/run_q_scaling_full_decomp_minp95.py\", line 89, in _worker\n    result = solve_full_milp(\n        workflow,\n    ...<4 lines>...\n        config,\n    )\n  File \"/Users/heng/Documents/skybridge/sim/src/milp_full.py\", line 50, in solve_full_milp\n    raise RuntimeError(f\"Full MILP failed to find a solution (status={status})\")\nRuntimeError: Full MILP failed to find a solution (status=TIME_LIMIT)\n",
    "process_exitcode": 0
  },
  {
    "workflow": "workflow1",
    "quality_level": "Q3",
    "query_count": 2000,
    "eta": 0.1,
    "calibration_scenarios_per_query": 50,
    "test_scenarios_per_query": 50,
    "calibration_scenario_count": 100000,
    "test_scenario_count": 100000,
    "method": "decomposed_milp",
    "solver_method": "decomposition",
    "status": "INFEASIBLE_REUSED_LAST_FEASIBLE",
    "reused_last_feasible": true,
    "objective_value": Infinity,
    "expected_cost": 6.98688679185177,
    "avg_latency": 3970.455454181018,
    "p95_latency": 11418.403539363046,
    "p99_latency": 19779.488089605566,
    "violation_rate": 0.06562,
    "solver_runtime_sec": 407.7369019580001,
    "wall_time_sec": 485.44801870899755,
    "max_rss_mb": 3200.96875,
    "num_iterations": 2,
    "active_scenario_count": 25000,
    "active_scenario_fraction": 0.25,
    "assignment_signature": "[[\"Q/A\", \"q_a_azure_eastus_q3\"], [\"Shot Detection\", \"shot_detection_aliyun_cn-shanghai_q3\"], [\"Video Caption\", \"video_caption_azure_eastus_q3\"], [\"Video Split & Sample\", \"video_split_and_sample_aliyun_cn-shanghai_q3\"]]",
    "error": "",
    "process_exitcode": 0
  },
  {
    "workflow": "workflow2",
    "quality_level": "Q1",
    "query_count": 200,
    "eta": 0.1,
    "calibration_scenarios_per_query": 50,
    "test_scenarios_per_query": NaN,
    "calibration_scenario_count": 10000,
    "test_scenario_count": NaN,
    "method": "full_milp",
    "solver_method": "",
    "status": "FAILED",
    "reused_last_feasible": false,
    "objective_value": NaN,
    "expected_cost": NaN,
    "avg_latency": NaN,
    "p95_latency": NaN,
    "p99_latency": NaN,
    "violation_rate": NaN,
    "solver_runtime_sec": NaN,
    "wall_time_sec": 128.89453995800068,
    "max_rss_mb": 6137.390625,
    "num_iterations": 0,
    "active_scenario_count": 0,
    "active_scenario_fraction": NaN,
    "assignment_signature": "",
    "error": "RuntimeError: Full MILP failed to find a solution (status=INFEASIBLE)\nTraceback (most recent call last):\n  File \"/Users/heng/Documents/skybridge/sim/scripts/run_q_scaling_full_decomp_minp95.py\", line 89, in _worker\n    result = solve_full_milp(\n        workflow,\n    ...<4 lines>...\n        config,\n    )\n  File \"/Users/heng/Documents/skybridge/sim/src/milp_full.py\", line 50, in solve_full_milp\n    raise RuntimeError(f\"Full MILP failed to find a solution (status={status})\")\nRuntimeError: Full MILP failed to find a solution (status=INFEASIBLE)\n",
    "process_exitcode": 0
  },
  {
    "workflow": "workflow2",
    "quality_level": "Q1",
    "query_count": 200,
    "eta": 0.1,
    "calibration_scenarios_per_query": 50,
    "test_scenarios_per_query": 50,
    "calibration_scenario_count": 10000,
    "test_scenario_count": 10000,
    "method": "decomposed_milp",
    "solver_method": "decomposition",
    "status": "INFEASIBLE_REUSED_LAST_FEASIBLE",
    "reused_last_feasible": true,
    "objective_value": Infinity,
    "expected_cost": 2.9383676223093653,
    "avg_latency": 549.9967403339335,
    "p95_latency": 1283.331017622443,
    "p99_latency": 1914.5668454524082,
    "violation_rate": 0.0313,
    "solver_runtime_sec": 80.20154625099894,
    "wall_time_sec": 135.1010970419993,
    "max_rss_mb": 2168.9375,
    "num_iterations": 3,
    "active_scenario_count": 2874,
    "active_scenario_fraction": 0.2874,
    "assignment_signature": "[[\"Database\", \"database_aliyun_cn-shanghai_q1\"], [\"Label Detection\", \"label_detection_aliyun_cn-shanghai_q1\"], [\"OCR\", \"ocr_azure_eastus_q1\"], [\"Q/A\", \"q_a_anthropic_global_q1\"], [\"Shot Detection\", \"shot_detection_aliyun_cn-shanghai_q1\"], [\"Speech Transcription\", \"speech_transcription_aliyun_cn-shanghai_q1\"], [\"Video Caption\", \"video_caption_aws_us-east-2_q1\"], [\"Video Split & Sample\", \"video_split_and_sample_aliyun_cn-shanghai_q1\"]]",
    "error": "",
    "process_exitcode": 0
  },
  {
    "workflow": "workflow2",
    "quality_level": "Q1",
    "query_count": 400,
    "eta": 0.1,
    "calibration_scenarios_per_query": 50,
    "test_scenarios_per_query": NaN,
    "calibration_scenario_count": 20000,
    "test_scenario_count": NaN,
    "method": "full_milp",
    "solver_method": "",
    "status": "FAILED",
    "reused_last_feasible": false,
    "objective_value": NaN,
    "expected_cost": NaN,
    "avg_latency": NaN,
    "p95_latency": NaN,
    "p99_latency": NaN,
    "violation_rate": NaN,
    "solver_runtime_sec": NaN,
    "wall_time_sec": 301.0874936670007,
    "max_rss_mb": 6524.6875,
    "num_iterations": 0,
    "active_scenario_count": 0,
    "active_scenario_fraction": NaN,
    "assignment_signature": "",
    "error": "RuntimeError: Full MILP failed to find a solution (status=INFEASIBLE)\nTraceback (most recent call last):\n  File \"/Users/heng/Documents/skybridge/sim/scripts/run_q_scaling_full_decomp_minp95.py\", line 89, in _worker\n    result = solve_full_milp(\n        workflow,\n    ...<4 lines>...\n        config,\n    )\n  File \"/Users/heng/Documents/skybridge/sim/src/milp_full.py\", line 50, in solve_full_milp\n    raise RuntimeError(f\"Full MILP failed to find a solution (status={status})\")\nRuntimeError: Full MILP failed to find a solution (status=INFEASIBLE)\n",
    "process_exitcode": 0
  },
  {
    "workflow": "workflow2",
    "quality_level": "Q1",
    "query_count": 400,
    "eta": 0.1,
    "calibration_scenarios_per_query": 50,
    "test_scenarios_per_query": 50,
    "calibration_scenario_count": 20000,
    "test_scenario_count": 20000,
    "method": "decomposed_milp",
    "solver_method": "decomposition",
    "status": "INFEASIBLE_REUSED_LAST_FEASIBLE",
    "reused_last_feasible": true,
    "objective_value": Infinity,
    "expected_cost": 2.901776846633135,
    "avg_latency": 539.651035154917,
    "p95_latency": 1284.8937015850895,
    "p99_latency": 1927.5170445819515,
    "violation_rate": 0.03105,
    "solver_runtime_sec": 195.54700729100296,
    "wall_time_sec": 295.95703100000173,
    "max_rss_mb": 4312.015625,
    "num_iterations": 3,
    "active_scenario_count": 6000,
    "active_scenario_fraction": 0.3,
    "assignment_signature": "[[\"Database\", \"database_aliyun_cn-shanghai_q1\"], [\"Label Detection\", \"label_detection_aliyun_cn-shanghai_q1\"], [\"OCR\", \"ocr_azure_eastus_q1\"], [\"Q/A\", \"q_a_anthropic_global_q1\"], [\"Shot Detection\", \"shot_detection_aliyun_cn-shanghai_q1\"], [\"Speech Transcription\", \"speech_transcription_aliyun_cn-shanghai_q1\"], [\"Video Caption\", \"video_caption_aws_us-east-2_q1\"], [\"Video Split & Sample\", \"video_split_and_sample_aliyun_cn-shanghai_q1\"]]",
    "error": "",
    "process_exitcode": 0
  },
  {
    "workflow": "workflow2",
    "quality_level": "Q1",
    "query_count": 600,
    "eta": 0.1,
    "calibration_scenarios_per_query": 50,
    "test_scenarios_per_query": NaN,
    "calibration_scenario_count": 30000,
    "test_scenario_count": NaN,
    "method": "full_milp",
    "solver_method": "",
    "status": "FAILED",
    "reused_last_feasible": false,
    "objective_value": NaN,
    "expected_cost": NaN,
    "avg_latency": NaN,
    "p95_latency": NaN,
    "p99_latency": NaN,
    "violation_rate": NaN,
    "solver_runtime_sec": NaN,
    "wall_time_sec": 450.58080629199685,
    "max_rss_mb": 7330.0625,
    "num_iterations": 0,
    "active_scenario_count": 0,
    "active_scenario_fraction": NaN,
    "assignment_signature": "",
    "error": "RuntimeError: Full MILP failed to find a solution (status=TIME_LIMIT)\nTraceback (most recent call last):\n  File \"/Users/heng/Documents/skybridge/sim/scripts/run_q_scaling_full_decomp_minp95.py\", line 89, in _worker\n    result = solve_full_milp(\n        workflow,\n    ...<4 lines>...\n        config,\n    )\n  File \"/Users/heng/Documents/skybridge/sim/src/milp_full.py\", line 50, in solve_full_milp\n    raise RuntimeError(f\"Full MILP failed to find a solution (status={status})\")\nRuntimeError: Full MILP failed to find a solution (status=TIME_LIMIT)\n",
    "process_exitcode": 0
  },
  {
    "workflow": "workflow2",
    "quality_level": "Q1",
    "query_count": 600,
    "eta": 0.1,
    "calibration_scenarios_per_query": 50,
    "test_scenarios_per_query": 50,
    "calibration_scenario_count": 30000,
    "test_scenario_count": 30000,
    "method": "decomposed_milp",
    "solver_method": "decomposition",
    "status": "INFEASIBLE_REUSED_LAST_FEASIBLE",
    "reused_last_feasible": true,
    "objective_value": Infinity,
    "expected_cost": 2.866231028774275,
    "avg_latency": 530.0482454257907,
    "p95_latency": 1271.0473042616309,
    "p99_latency": 1961.7271700895492,
    "violation_rate": 0.03186666666666667,
    "solver_runtime_sec": 339.7375819989975,
    "wall_time_sec": 482.4644225419979,
    "max_rss_mb": 6430.125,
    "num_iterations": 3,
    "active_scenario_count": 9000,
    "active_scenario_fraction": 0.3,
    "assignment_signature": "[[\"Database\", \"database_aliyun_cn-shanghai_q1\"], [\"Label Detection\", \"label_detection_aliyun_cn-shanghai_q1\"], [\"OCR\", \"ocr_azure_eastus_q1\"], [\"Q/A\", \"q_a_anthropic_global_q1\"], [\"Shot Detection\", \"shot_detection_aliyun_cn-shanghai_q1\"], [\"Speech Transcription\", \"speech_transcription_aliyun_cn-shanghai_q1\"], [\"Video Caption\", \"video_caption_aws_us-east-2_q1\"], [\"Video Split & Sample\", \"video_split_and_sample_aliyun_cn-shanghai_q1\"]]",
    "error": "",
    "process_exitcode": 0
  },
  {
    "workflow": "workflow2",
    "quality_level": "Q1",
    "query_count": 800,
    "eta": 0.1,
    "calibration_scenarios_per_query": 50,
    "test_scenarios_per_query": NaN,
    "calibration_scenario_count": 40000,
    "test_scenario_count": NaN,
    "method": "full_milp",
    "solver_method": "",
    "status": "FAILED",
    "reused_last_feasible": false,
    "objective_value": NaN,
    "expected_cost": NaN,
    "avg_latency": NaN,
    "p95_latency": NaN,
    "p99_latency": NaN,
    "violation_rate": NaN,
    "solver_runtime_sec": NaN,
    "wall_time_sec": 485.01915750000626,
    "max_rss_mb": 7000.109375,
    "num_iterations": 0,
    "active_scenario_count": 0,
    "active_scenario_fraction": NaN,
    "assignment_signature": "",
    "error": "RuntimeError: Full MILP failed to find a solution (status=TIME_LIMIT)\nTraceback (most recent call last):\n  File \"/Users/heng/Documents/skybridge/sim/scripts/run_q_scaling_full_decomp_minp95.py\", line 89, in _worker\n    result = solve_full_milp(\n        workflow,\n    ...<4 lines>...\n        config,\n    )\n  File \"/Users/heng/Documents/skybridge/sim/src/milp_full.py\", line 50, in solve_full_milp\n    raise RuntimeError(f\"Full MILP failed to find a solution (status={status})\")\nRuntimeError: Full MILP failed to find a solution (status=TIME_LIMIT)\n",
    "process_exitcode": 0
  },
  {
    "workflow": "workflow2",
    "quality_level": "Q1",
    "query_count": 800,
    "eta": 0.1,
    "calibration_scenarios_per_query": 50,
    "test_scenarios_per_query": 50,
    "calibration_scenario_count": 40000,
    "test_scenario_count": 40000,
    "method": "decomposed_milp",
    "solver_method": "decomposition",
    "status": "INFEASIBLE_REUSED_LAST_FEASIBLE",
    "reused_last_feasible": true,
    "objective_value": Infinity,
    "expected_cost": 2.861647457125679,
    "avg_latency": 522.1300939527416,
    "p95_latency": 1255.1218090598106,
    "p99_latency": 1949.158604252596,
    "violation_rate": 0.03175,
    "solver_runtime_sec": 499.1637779579978,
    "wall_time_sec": 685.2442515839939,
    "max_rss_mb": 7940.0625,
    "num_iterations": 3,
    "active_scenario_count": 12000,
    "active_scenario_fraction": 0.3,
    "assignment_signature": "[[\"Database\", \"database_aliyun_cn-shanghai_q1\"], [\"Label Detection\", \"label_detection_aliyun_cn-shanghai_q1\"], [\"OCR\", \"ocr_azure_eastus_q1\"], [\"Q/A\", \"q_a_aws_ap-southeast-1_q1\"], [\"Shot Detection\", \"shot_detection_aliyun_cn-shanghai_q1\"], [\"Speech Transcription\", \"speech_transcription_aliyun_cn-shanghai_q1\"], [\"Video Caption\", \"video_caption_aws_ap-southeast-1_q1\"], [\"Video Split & Sample\", \"video_split_and_sample_aliyun_cn-shanghai_q1\"]]",
    "error": "",
    "process_exitcode": 0
  },
  {
    "workflow": "workflow2",
    "quality_level": "Q1",
    "query_count": 1000,
    "eta": 0.1,
    "calibration_scenarios_per_query": 50,
    "test_scenarios_per_query": NaN,
    "calibration_scenario_count": 50000,
    "test_scenario_count": NaN,
    "method": "full_milp",
    "solver_method": "",
    "status": "FAILED",
    "reused_last_feasible": false,
    "objective_value": NaN,
    "expected_cost": NaN,
    "avg_latency": NaN,
    "p95_latency": NaN,
    "p99_latency": NaN,
    "violation_rate": NaN,
    "solver_runtime_sec": NaN,
    "wall_time_sec": 546.9199346250025,
    "max_rss_mb": 8395.78125,
    "num_iterations": 0,
    "active_scenario_count": 0,
    "active_scenario_fraction": NaN,
    "assignment_signature": "",
    "error": "RuntimeError: Full MILP failed to find a solution (status=TIME_LIMIT)\nTraceback (most recent call last):\n  File \"/Users/heng/Documents/skybridge/sim/scripts/run_q_scaling_full_decomp_minp95.py\", line 89, in _worker\n    result = solve_full_milp(\n        workflow,\n    ...<4 lines>...\n        config,\n    )\n  File \"/Users/heng/Documents/skybridge/sim/src/milp_full.py\", line 50, in solve_full_milp\n    raise RuntimeError(f\"Full MILP failed to find a solution (status={status})\")\nRuntimeError: Full MILP failed to find a solution (status=TIME_LIMIT)\n",
    "process_exitcode": 0
  },
  {
    "workflow": "workflow2",
    "quality_level": "Q1",
    "query_count": 1000,
    "eta": 0.1,
    "calibration_scenarios_per_query": 50,
    "test_scenarios_per_query": 50,
    "calibration_scenario_count": 50000,
    "test_scenario_count": 50000,
    "method": "decomposed_milp",
    "solver_method": "decomposition",
    "status": "INFEASIBLE_REUSED_LAST_FEASIBLE",
    "reused_last_feasible": true,
    "objective_value": Infinity,
    "expected_cost": 2.8695574875864516,
    "avg_latency": 529.9732303969854,
    "p95_latency": 1268.2975626628715,
    "p99_latency": 1952.1076145826546,
    "violation_rate": 0.03148,
    "solver_runtime_sec": 638.3298702489992,
    "wall_time_sec": 867.1909156670008,
    "max_rss_mb": 8718.234375,
    "num_iterations": 3,
    "active_scenario_count": 15000,
    "active_scenario_fraction": 0.3,
    "assignment_signature": "[[\"Database\", \"database_aliyun_cn-shanghai_q1\"], [\"Label Detection\", \"label_detection_aliyun_cn-shanghai_q1\"], [\"OCR\", \"ocr_azure_eastus_q1\"], [\"Q/A\", \"q_a_anthropic_global_q1\"], [\"Shot Detection\", \"shot_detection_aliyun_cn-shanghai_q1\"], [\"Speech Transcription\", \"speech_transcription_aliyun_cn-shanghai_q1\"], [\"Video Caption\", \"video_caption_aws_us-east-2_q1\"], [\"Video Split & Sample\", \"video_split_and_sample_aliyun_cn-shanghai_q1\"]]",
    "error": "",
    "process_exitcode": 0
  },
  {
    "workflow": "workflow2",
    "quality_level": "Q1",
    "query_count": 1200,
    "eta": 0.1,
    "calibration_scenarios_per_query": 50,
    "test_scenarios_per_query": NaN,
    "calibration_scenario_count": 60000,
    "test_scenario_count": NaN,
    "method": "full_milp",
    "solver_method": "",
    "status": "FAILED",
    "reused_last_feasible": false,
    "objective_value": NaN,
    "expected_cost": NaN,
    "avg_latency": NaN,
    "p95_latency": NaN,
    "p99_latency": NaN,
    "violation_rate": NaN,
    "solver_runtime_sec": NaN,
    "wall_time_sec": 613.6738640830008,
    "max_rss_mb": 8735.296875,
    "num_iterations": 0,
    "active_scenario_count": 0,
    "active_scenario_fraction": NaN,
    "assignment_signature": "",
    "error": "RuntimeError: Full MILP failed to find a solution (status=TIME_LIMIT)\nTraceback (most recent call last):\n  File \"/Users/heng/Documents/skybridge/sim/scripts/run_q_scaling_full_decomp_minp95.py\", line 89, in _worker\n    result = solve_full_milp(\n        workflow,\n    ...<4 lines>...\n        config,\n    )\n  File \"/Users/heng/Documents/skybridge/sim/src/milp_full.py\", line 50, in solve_full_milp\n    raise RuntimeError(f\"Full MILP failed to find a solution (status={status})\")\nRuntimeError: Full MILP failed to find a solution (status=TIME_LIMIT)\n",
    "process_exitcode": 0
  },
  {
    "workflow": "workflow2",
    "quality_level": "Q1",
    "query_count": 1200,
    "eta": 0.1,
    "calibration_scenarios_per_query": 50,
    "test_scenarios_per_query": 50,
    "calibration_scenario_count": 60000,
    "test_scenario_count": 60000,
    "method": "decomposed_milp",
    "solver_method": "decomposition",
    "status": "INFEASIBLE_REUSED_LAST_FEASIBLE",
    "reused_last_feasible": true,
    "objective_value": Infinity,
    "expected_cost": 2.862705880051365,
    "avg_latency": 527.79999391332,
    "p95_latency": 1263.4107613400881,
    "p99_latency": 1950.9226152995993,
    "violation_rate": 0.03155,
    "solver_runtime_sec": 972.3916432490005,
    "wall_time_sec": 1236.9134935409966,
    "max_rss_mb": 9119.96875,
    "num_iterations": 3,
    "active_scenario_count": 17556,
    "active_scenario_fraction": 0.2926,
    "assignment_signature": "[[\"Database\", \"database_aliyun_cn-shanghai_q1\"], [\"Label Detection\", \"label_detection_aliyun_cn-shanghai_q1\"], [\"OCR\", \"ocr_azure_eastus_q1\"], [\"Q/A\", \"q_a_aws_eu-central-1_q1\"], [\"Shot Detection\", \"shot_detection_aliyun_cn-shanghai_q1\"], [\"Speech Transcription\", \"speech_transcription_aliyun_cn-shanghai_q1\"], [\"Video Caption\", \"video_caption_aws_us-east-2_q1\"], [\"Video Split & Sample\", \"video_split_and_sample_aliyun_cn-shanghai_q1\"]]",
    "error": "",
    "process_exitcode": 0
  },
  {
    "workflow": "workflow2",
    "quality_level": "Q1",
    "query_count": 1400,
    "eta": 0.1,
    "calibration_scenarios_per_query": 50,
    "test_scenarios_per_query": NaN,
    "calibration_scenario_count": 70000,
    "test_scenario_count": NaN,
    "method": "full_milp",
    "solver_method": "",
    "status": "FAILED",
    "reused_last_feasible": false,
    "objective_value": NaN,
    "expected_cost": NaN,
    "avg_latency": NaN,
    "p95_latency": NaN,
    "p99_latency": NaN,
    "violation_rate": NaN,
    "solver_runtime_sec": NaN,
    "wall_time_sec": 611.7970566669974,
    "max_rss_mb": 8572.390625,
    "num_iterations": 0,
    "active_scenario_count": 0,
    "active_scenario_fraction": NaN,
    "assignment_signature": "",
    "error": "RuntimeError: Full MILP failed to find a solution (status=TIME_LIMIT)\nTraceback (most recent call last):\n  File \"/Users/heng/Documents/skybridge/sim/scripts/run_q_scaling_full_decomp_minp95.py\", line 89, in _worker\n    result = solve_full_milp(\n        workflow,\n    ...<4 lines>...\n        config,\n    )\n  File \"/Users/heng/Documents/skybridge/sim/src/milp_full.py\", line 50, in solve_full_milp\n    raise RuntimeError(f\"Full MILP failed to find a solution (status={status})\")\nRuntimeError: Full MILP failed to find a solution (status=TIME_LIMIT)\n",
    "process_exitcode": 0
  },
  {
    "workflow": "workflow2",
    "quality_level": "Q1",
    "query_count": 1400,
    "eta": 0.1,
    "calibration_scenarios_per_query": 50,
    "test_scenarios_per_query": 50,
    "calibration_scenario_count": 70000,
    "test_scenario_count": 70000,
    "method": "decomposed_milp",
    "solver_method": "decomposition",
    "status": "TIME_LIMIT_REUSED_LAST_FEASIBLE",
    "reused_last_feasible": true,
    "objective_value": Infinity,
    "expected_cost": 2.8716404238158315,
    "avg_latency": 530.4516817124014,
    "p95_latency": 1267.252470683003,
    "p99_latency": 1946.5382858728437,
    "violation_rate": 0.0314,
    "solver_runtime_sec": 1119.7845768760017,
    "wall_time_sec": 1436.5401917080017,
    "max_rss_mb": 9111.84375,
    "num_iterations": 3,
    "active_scenario_count": 21000,
    "active_scenario_fraction": 0.3,
    "assignment_signature": "[[\"Database\", \"database_aliyun_cn-shanghai_q1\"], [\"Label Detection\", \"label_detection_aliyun_cn-shanghai_q1\"], [\"OCR\", \"ocr_azure_eastus_q1\"], [\"Q/A\", \"q_a_anthropic_global_q1\"], [\"Shot Detection\", \"shot_detection_aliyun_cn-shanghai_q1\"], [\"Speech Transcription\", \"speech_transcription_aliyun_cn-shanghai_q1\"], [\"Video Caption\", \"video_caption_aws_us-east-2_q1\"], [\"Video Split & Sample\", \"video_split_and_sample_aliyun_cn-shanghai_q1\"]]",
    "error": "",
    "process_exitcode": 0
  },
  {
    "workflow": "workflow2",
    "quality_level": "Q1",
    "query_count": 1600,
    "eta": 0.1,
    "calibration_scenarios_per_query": 50,
    "test_scenarios_per_query": NaN,
    "calibration_scenario_count": 80000,
    "test_scenario_count": NaN,
    "method": "full_milp",
    "solver_method": "",
    "status": "FAILED",
    "reused_last_feasible": false,
    "objective_value": NaN,
    "expected_cost": NaN,
    "avg_latency": NaN,
    "p95_latency": NaN,
    "p99_latency": NaN,
    "violation_rate": NaN,
    "solver_runtime_sec": NaN,
    "wall_time_sec": 868.9875337079939,
    "max_rss_mb": 8402.078125,
    "num_iterations": 0,
    "active_scenario_count": 0,
    "active_scenario_fraction": NaN,
    "assignment_signature": "",
    "error": "RuntimeError: Full MILP failed to find a solution (status=TIME_LIMIT)\nTraceback (most recent call last):\n  File \"/Users/heng/Documents/skybridge/sim/scripts/run_q_scaling_full_decomp_minp95.py\", line 89, in _worker\n    result = solve_full_milp(\n        workflow,\n    ...<4 lines>...\n        config,\n    )\n  File \"/Users/heng/Documents/skybridge/sim/src/milp_full.py\", line 50, in solve_full_milp\n    raise RuntimeError(f\"Full MILP failed to find a solution (status={status})\")\nRuntimeError: Full MILP failed to find a solution (status=TIME_LIMIT)\n",
    "process_exitcode": 0
  }
]